{
  "matchId": "EUW1_7565883520",
  "gameDate": "2025-10-12 19:43:06",
  "rank": "PLATINUM IV",
  "gameMode": "CLASSIC",
  "gameDuration": 1861,
  "timestamps_minutes": [
    0.0,
    1.00045,
    2.00085,
    3.0023166666666667,
    4.00255,
    5.0027333333333335,
    6.003216666666667,
    7.0035,
    8.004033333333334,
    9.0045,
    10.005016666666666,
    11.00535,
    12.005483333333334,
    13.005916666666666,
    14.005916666666666,
    15.006016666666667,
    16.006483333333332,
    17.006783333333335,
    18.006933333333333,
    19.00711666666667,
    20.007283333333334,
    21.007516666666668,
    22.007716666666667,
    23.007883333333332,
    24.007933333333334,
    25.0082,
    26.008266666666668,
    27.008583333333334,
    28.0087,
    29.008783333333334,
    30.009066666666666,
    31.0096,
    31.026316666666666
  ],
  "participants": [
    {
      "participantId": 1,
      "championName": "Ambessa",
      "teamId": 100,
      "win": true,
      "lane": "TOP",
      "gold_curve": [
        500,
        500,
        583,
        881,
        1157,
        1285,
        1676,
        2049,
        2363,
        2984,
        3255,
        3790,
        4343,
        4686,
        4933,
        5445,
        6164,
        6574,
        6983,
        7147,
        7479,
        7602,
        8318,
        8741,
        8996,
        9757,
        10242,
        10573,
        12371,
        12667,
        13402,
        14239,
        14240
      ],
      "item_purchases": [
        {
          "type": "ITEM_PURCHASED",
          "timestamp": 16437,
          "itemId": 1054
        },
        {
          "type": "ITEM_PURCHASED",
          "timestamp": 16437,
          "itemId": 2003
        },
        {
          "type": "ITEM_DESTROYED",
          "timestamp": 218061,
          "itemId": 2003
        },
        {
          "type": "ITEM_DESTROYED",
          "timestamp": 245499,
          "itemId": 2010
        },
        {
          "type": "ITEM_PURCHASED",
          "timestamp": 275427,
          "itemId": 1036
        },
        {
          "type": "ITEM_PURCHASED",
          "timestamp": 275628,
          "itemId": 1036
        },
        {
          "type": "ITEM_PURCHASED",
          "timestamp": 432702,
          "itemId": 1037
        },
        {
          "type": "ITEM_DESTROYED",
          "timestamp": 464099,
          "itemId": 2010
        },
        {
          "type": "ITEM_DESTROYED",
          "timestamp": 537774,
          "itemId": 1036
        },
        {
          "type": "ITEM_DESTROYED",
          "timestamp": 537774,
          "itemId": 1036
        },
        {
          "type": "ITEM_PURCHASED",
          "timestamp": 537774,
          "itemId": 3133
        },
        {
          "type": "ITEM_PURCHASED",
          "timestamp": 538141,
          "itemId": 1036
        },
        {
          "type": "ITEM_PURCHASED",
          "timestamp": 540807,
          "itemId": 2031
        },
        {
          "type": "ITEM_DESTROYED",
          "timestamp": 632352,
          "itemId": 3133
        },
        {
          "type": "ITEM_DESTROYED",
          "timestamp": 632352,
          "itemId": 1037
        },
        {
          "type": "ITEM_DESTROYED",
          "timestamp": 632352,
          "itemId": 1036
        },
        {
          "type": "ITEM_PURCHASED",
          "timestamp": 632352,
          "itemId": 6692
        },
        {
          "type": "ITEM_PURCHASED",
          "timestamp": 724471,
          "itemId": 1029
        },
        {
          "type": "ITEM_SOLD",
          "timestamp": 727212,
          "itemId": 2031
        },
        {
          "type": "ITEM_PURCHASED",
          "timestamp": 727546,
          "itemId": 1028
        },
        {
          "type": "ITEM_DESTROYED",
          "timestamp": 836318,
          "itemId": 2010
        },
        {
          "type": "ITEM_DESTROYED",
          "timestamp": 873283,
          "itemId": 2422
        },
        {
          "type": "ITEM_DESTROYED",
          "timestamp": 873283,
          "itemId": 1029
        },
        {
          "type": "ITEM_PURCHASED",
          "timestamp": 873283,
          "itemId": 3047
        },
        {
          "type": "ITEM_PURCHASED",
          "timestamp": 874285,
          "itemId": 1036
        },
        {
          "type": "ITEM_PURCHASED",
          "timestamp": 928654,
          "itemId": 1037
        },
        {
          "type": "ITEM_DESTROYED",
          "timestamp": 1102695,
          "itemId": 1036
        },
        {
          "type": "ITEM_DESTROYED",
          "timestamp": 1102695,
          "itemId": 1028
        },
        {
          "type": "ITEM_PURCHASED",
          "timestamp": 1102695,
          "itemId": 2021
        },
        {
          "type": "ITEM_PURCHASED",
          "timestamp": 1102995,
          "itemId": 1028
        },
        {
          "type": "ITEM_DESTROYED",
          "timestamp": 1207318,
          "itemId": 1037
        },
        {
          "type": "ITEM_DESTROYED",
          "timestamp": 1207318,
          "itemId": 2021
        },
        {
          "type": "ITEM_DESTROYED",
          "timestamp": 1207318,
          "itemId": 1028
        },
        {
          "type": "ITEM_PURCHASED",
          "timestamp": 1207318,
          "itemId": 3161
        },
        {
          "type": "ITEM_PURCHASED",
          "timestamp": 1412531,
          "itemId": 3123
        },
        {
          "type": "ITEM_PURCHASED",
          "timestamp": 1414268,
          "itemId": 1036
        },
        {
          "type": "ITEM_DESTROYED",
          "timestamp": 1520561,
          "itemId": 1036
        },
        {
          "type": "ITEM_PURCHASED",
          "timestamp": 1520561,
          "itemId": 2019
        },
        {
          "type": "ITEM_SOLD",
          "timestamp": 1523836,
          "itemId": 1054
        },
        {
          "type": "ITEM_PURCHASED",
          "timestamp": 1524137,
          "itemId": 1037
        },
        {
          "type": "ITEM_DESTROYED",
          "timestamp": 1713636,
          "itemId": 2019
        },
        {
          "type": "ITEM_DESTROYED",
          "timestamp": 1713636,
          "itemId": 1037
        },
        {
          "type": "ITEM_PURCHASED",
          "timestamp": 1713636,
          "itemId": 6333
        },
        {
          "type": "ITEM_PURCHASED",
          "timestamp": 1718935,
          "itemId": 2021
        }
      ],
      "final_items": [
        3047,
        3161,
        6333,
        6692,
        3123,
        2021,
        3340
      ]
    },
    {
      "participantId": 2,
      "championName": "Sejuani",
      "teamId": 100,
      "win": true,
      "lane": "JUNGLE",
      "gold_curve": [
        500,
        500,
        631,
        1013,
        1355,
        1607,
        1909,
        2174,
        2502,
        2899,
        3053,
        3497,
        3837,
        4199,
        4596,
        4827,
        5155,
        5698,
        6163,
        6579,
        6736,
        6924,
        7312,
        7592,
        8310,
        8831,
        9298,
        9601,
        10394,
        10632,
        11236,
        11718,
        11719
      ],
      "item_purchases": [
        {
          "type": "ITEM_PURCHASED",
          "timestamp": 20111,
          "itemId": 1102
        },
        {
          "type": "ITEM_DESTROYED",
          "timestamp": 54315,
          "itemId": 3340
        },
        {
          "type": "ITEM_PURCHASED",
          "timestamp": 54315,
          "itemId": 3364
        },
        {
          "type": "ITEM_PURCHASED",
          "timestamp": 242960,
          "itemId": 1031
        },
        {
          "type": "ITEM_PURCHASED",
          "timestamp": 379598,
          "itemId": 1028
        },
        {
          "type": "ITEM_PURCHASED",
          "timestamp": 380133,
          "itemId": 2022
        },
        {
          "type": "ITEM_DESTROYED",
          "timestamp": 696978,
          "itemId": 1028
        },
        {
          "type": "ITEM_DESTROYED",
          "timestamp": 696978,
          "itemId": 2022
        },
        {
          "type": "ITEM_DESTROYED",
          "timestamp": 696978,
          "itemId": 1031
        },
        {
          "type": "ITEM_PURCHASED",
          "timestamp": 696978,
          "itemId": 3068
        },
        {
          "type": "ITEM_PURCHASED",
          "timestamp": 699015,
          "itemId": 1001
        },
        {
          "type": "ITEM_PURCHASED",
          "timestamp": 700017,
          "itemId": 1029
        },
        {
          "type": "ITEM_DESTROYED",
          "timestamp": 866369,
          "itemId": 1001
        },
        {
          "type": "ITEM_DESTROYED",
          "timestamp": 866369,
          "itemId": 1029
        },
        {
          "type": "ITEM_PURCHASED",
          "timestamp": 866369,
          "itemId": 3047
        },
        {
          "type": "ITEM_PURCHASED",
          "timestamp": 870678,
          "itemId": 1029
        },
        {
          "type": "ITEM_PURCHASED",
          "timestamp": 921907,
          "itemId": 1029
        },
        {
          "type": "ITEM_DESTROYED",
          "timestamp": 1003044,
          "itemId": 1102
        },
        {
          "type": "ITEM_DESTROYED",
          "timestamp": 1073328,
          "itemId": 1029
        },
        {
          "type": "ITEM_DESTROYED",
          "timestamp": 1073328,
          "itemId": 1029
        },
        {
          "type": "ITEM_PURCHASED",
          "timestamp": 1073328,
          "itemId": 3076
        },
        {
          "type": "ITEM_PURCHASED",
          "timestamp": 1073969,
          "itemId": 1031
        },
        {
          "type": "ITEM_PURCHASED",
          "timestamp": 1166075,
          "itemId": 1028
        },
        {
          "type": "ITEM_DESTROYED",
          "timestamp": 1331512,
          "itemId": 3076
        },
        {
          "type": "ITEM_DESTROYED",
          "timestamp": 1331512,
          "itemId": 1031
        },
        {
          "type": "ITEM_DESTROYED",
          "timestamp": 1331512,
          "itemId": 1028
        },
        {
          "type": "ITEM_PURCHASED",
          "timestamp": 1331512,
          "itemId": 3075
        },
        {
          "type": "ITEM_PURCHASED",
          "timestamp": 1333282,
          "itemId": 1029
        },
        {
          "type": "ITEM_PURCHASED",
          "timestamp": 1334073,
          "itemId": 1029
        },
        {
          "type": "ITEM_DESTROYED",
          "timestamp": 1597409,
          "itemId": 1029
        },
        {
          "type": "ITEM_DESTROYED",
          "timestamp": 1597409,
          "itemId": 1029
        },
        {
          "type": "ITEM_PURCHASED",
          "timestamp": 1597409,
          "itemId": 3110
        },
        {
          "type": "ITEM_PURCHASED",
          "timestamp": 1655631,
          "itemId": 1057
        },
        {
          "type": "ITEM_PURCHASED",
          "timestamp": 1818527,
          "itemId": 1033
        }
      ],
      "final_items": [
        3075,
        3068,
        3047,
        3110,
        1057,
        1033,
        3364
      ]
    },
    {
      "participantId": 3,
      "championName": "Akshan",
      "teamId": 100,
      "win": true,
      "lane": "MIDDLE",
      "gold_curve": [
        500,
        500,
        888,
        1192,
        1392,
        2017,
        2293,
        2757,
        2949,
        3360,
        3576,
        4000,
        4311,
        5156,
        5383,
        5652,
        5981,
        6386,
        7142,
        7461,
        7741,
        8704,
        9120,
        9417,
        10049,
        11119,
        11923,
        12451,
        13414,
        13921,
        14093,
        15710,
        15711
      ],
      "item_purchases": [
        {
          "type": "ITEM_PURCHASED",
          "timestamp": 22383,
          "itemId": 1055
        },
        {
          "type": "ITEM_PURCHASED",
          "timestamp": 22383,
          "itemId": 2003
        },
        {
          "type": "ITEM_PURCHASED",
          "timestamp": 22817,
          "itemId": 3340
        },
        {
          "type": "ITEM_DESTROYED",
          "timestamp": 116677,
          "itemId": 2003
        },
        {
          "type": "ITEM_PURCHASED",
          "timestamp": 207100,
          "itemId": 6690
        },
        {
          "type": "ITEM_PURCHASED",
          "timestamp": 304351,
          "itemId": 3144
        },
        {
          "type": "ITEM_PURCHASED",
          "timestamp": 416717,
          "itemId": 1037
        },
        {
          "type": "ITEM_DESTROYED",
          "timestamp": 535269,
          "itemId": 3144
        },
        {
          "type": "ITEM_DESTROYED",
          "timestamp": 535269,
          "itemId": 6690
        },
        {
          "type": "ITEM_DESTROYED",
          "timestamp": 535269,
          "itemId": 1037
        },
        {
          "type": "ITEM_PURCHASED",
          "timestamp": 535269,
          "itemId": 3087
        },
        {
          "type": "ITEM_PURCHASED",
          "timestamp": 709495,
          "itemId": 3134
        },
        {
          "type": "ITEM_PURCHASED",
          "timestamp": 833412,
          "itemId": 1037
        },
        {
          "type": "ITEM_PURCHASED",
          "timestamp": 920704,
          "itemId": 1018
        },
        {
          "type": "ITEM_DESTROYED",
          "timestamp": 1016708,
          "itemId": 1037
        },
        {
          "type": "ITEM_DESTROYED",
          "timestamp": 1016708,
          "itemId": 3134
        },
        {
          "type": "ITEM_DESTROYED",
          "timestamp": 1016708,
          "itemId": 1018
        },
        {
          "type": "ITEM_PURCHASED",
          "timestamp": 1016708,
          "itemId": 6676
        },
        {
          "type": "ITEM_PURCHASED",
          "timestamp": 1160932,
          "itemId": 3006
        },
        {
          "type": "ITEM_PURCHASED",
          "timestamp": 1297166,
          "itemId": 1038
        },
        {
          "type": "ITEM_PURCHASED",
          "timestamp": 1420860,
          "itemId": 1037
        },
        {
          "type": "ITEM_DESTROYED",
          "timestamp": 1547807,
          "itemId": 1038
        },
        {
          "type": "ITEM_DESTROYED",
          "timestamp": 1547807,
          "itemId": 1037
        },
        {
          "type": "ITEM_PURCHASED",
          "timestamp": 1547807,
          "itemId": 3031
        },
        {
          "type": "ITEM_PURCHASED",
          "timestamp": 1549778,
          "itemId": 1018
        },
        {
          "type": "ITEM_DESTROYED",
          "timestamp": 1655263,
          "itemId": 1018
        },
        {
          "type": "ITEM_PURCHASED",
          "timestamp": 1655263,
          "itemId": 6670
        },
        {
          "type": "ITEM_DESTROYED",
          "timestamp": 1744061,
          "itemId": 6670
        },
        {
          "type": "ITEM_PURCHASED",
          "timestamp": 1744061,
          "itemId": 3036
        }
      ],
      "final_items": [
        1055,
        3087,
        6676,
        3006,
        3031,
        3036,
        3340
      ]
    },
    {
      "participantId": 4,
      "championName": "Caitlyn",
      "teamId": 100,
      "win": true,
      "lane": "BOTTOM",
      "gold_curve": [
        500,
        512,
        650,
        954,
        1418,
        1807,
        2042,
        2428,
        2655,
        3021,
        3428,
        3907,
        4112,
        4844,
        5106,
        5388,
        7420,
        8314,
        8450,
        8851,
        10666,
        10907,
        11607,
        12020,
        13826,
        14733,
        15630,
        16272,
        17139,
        17706,
        19534,
        20148,
        20149
      ],
      "item_purchases": [
        {
          "type": "ITEM_PURCHASED",
          "timestamp": 3410,
          "itemId": 1055
        },
        {
          "type": "ITEM_PURCHASED",
          "timestamp": 3410,
          "itemId": 2003
        },
        {
          "type": "ITEM_PURCHASED",
          "timestamp": 219665,
          "itemId": 1037
        },
        {
          "type": "ITEM_DESTROYED",
          "timestamp": 358790,
          "itemId": 2003
        },
        {
          "type": "ITEM_PURCHASED",
          "timestamp": 451396,
          "itemId": 3134
        },
        {
          "type": "ITEM_PURCHASED",
          "timestamp": 452509,
          "itemId": 2031
        },
        {
          "type": "ITEM_PURCHASED",
          "timestamp": 455715,
          "itemId": 2055
        },
        {
          "type": "ITEM_PURCHASED",
          "timestamp": 456049,
          "itemId": 2031
        },
        {
          "type": "ITEM_DESTROYED",
          "timestamp": 521973,
          "itemId": 2055
        },
        {
          "type": "ITEM_DESTROYED",
          "timestamp": 554239,
          "itemId": 2010
        },
        {
          "type": "ITEM_PURCHASED",
          "timestamp": 568832,
          "itemId": 1018
        },
        {
          "type": "ITEM_DESTROYED",
          "timestamp": 631316,
          "itemId": 2010
        },
        {
          "type": "ITEM_DESTROYED",
          "timestamp": 682023,
          "itemId": 2010
        },
        {
          "type": "ITEM_DESTROYED",
          "timestamp": 703125,
          "itemId": 1037
        },
        {
          "type": "ITEM_DESTROYED",
          "timestamp": 703125,
          "itemId": 3134
        },
        {
          "type": "ITEM_DESTROYED",
          "timestamp": 703125,
          "itemId": 1018
        },
        {
          "type": "ITEM_PURCHASED",
          "timestamp": 703125,
          "itemId": 6676
        },
        {
          "type": "ITEM_PURCHASED",
          "timestamp": 703727,
          "itemId": 1042
        },
        {
          "type": "ITEM_DESTROYED",
          "timestamp": 816108,
          "itemId": 2422
        },
        {
          "type": "ITEM_DESTROYED",
          "timestamp": 816108,
          "itemId": 1042
        },
        {
          "type": "ITEM_PURCHASED",
          "timestamp": 816108,
          "itemId": 3006
        },
        {
          "type": "ITEM_PURCHASED",
          "timestamp": 878293,
          "itemId": 1018
        },
        {
          "type": "ITEM_PURCHASED",
          "timestamp": 959254,
          "itemId": 1038
        },
        {
          "type": "ITEM_SOLD",
          "timestamp": 960556,
          "itemId": 2031
        },
        {
          "type": "ITEM_PURCHASED",
          "timestamp": 961659,
          "itemId": 1037
        },
        {
          "type": "ITEM_DESTROYED",
          "timestamp": 1020240,
          "itemId": 1038
        },
        {
          "type": "ITEM_DESTROYED",
          "timestamp": 1020240,
          "itemId": 1037
        },
        {
          "type": "ITEM_DESTROYED",
          "timestamp": 1020240,
          "itemId": 1018
        },
        {
          "type": "ITEM_PURCHASED",
          "timestamp": 1020240,
          "itemId": 3031
        },
        {
          "type": "ITEM_PURCHASED",
          "timestamp": 1021776,
          "itemId": 1042
        },
        {
          "type": "ITEM_DESTROYED",
          "timestamp": 1027956,
          "itemId": 3340
        },
        {
          "type": "ITEM_PURCHASED",
          "timestamp": 1027956,
          "itemId": 3363
        },
        {
          "type": "ITEM_PURCHASED",
          "timestamp": 1116124,
          "itemId": 1018
        },
        {
          "type": "ITEM_DESTROYED",
          "timestamp": 1211829,
          "itemId": 1018
        },
        {
          "type": "ITEM_DESTROYED",
          "timestamp": 1211829,
          "itemId": 1042
        },
        {
          "type": "ITEM_PURCHASED",
          "timestamp": 1211829,
          "itemId": 3094
        },
        {
          "type": "ITEM_PURCHASED",
          "timestamp": 1309778,
          "itemId": 3123
        },
        {
          "type": "ITEM_DESTROYED",
          "timestamp": 1470642,
          "itemId": 3123
        },
        {
          "type": "ITEM_PURCHASED",
          "timestamp": 1470642,
          "itemId": 3033
        },
        {
          "type": "ITEM_SOLD",
          "timestamp": 1473358,
          "itemId": 1055
        },
        {
          "type": "ITEM_PURCHASED",
          "timestamp": 1474212,
          "itemId": 1053
        },
        {
          "type": "ITEM_DESTROYED",
          "timestamp": 1696163,
          "itemId": 1053
        },
        {
          "type": "ITEM_PURCHASED",
          "timestamp": 1696163,
          "itemId": 3072
        },
        {
          "type": "ITEM_SOLD",
          "timestamp": 1824168,
          "itemId": 3006
        },
        {
          "type": "ITEM_PURCHASED",
          "timestamp": 1825337,
          "itemId": 6701
        },
        {
          "type": "ITEM_DESTROYED",
          "timestamp": 1826439,
          "itemId": 2140
        },
        {
          "type": "ITEM_PURCHASED",
          "timestamp": 1826439,
          "itemId": 2140
        }
      ],
      "final_items": [
        6701,
        3031,
        6676,
        3094,
        3072,
        3033,
        3363
      ]
    },
    {
      "participantId": 5,
      "championName": "Brand",
      "teamId": 100,
      "win": true,
      "lane": "UTILITY",
      "gold_curve": [
        500,
        505,
        567,
        789,
        1156,
        1361,
        1557,
        1742,
        1949,
        2178,
        2362,
        2709,
        2905,
        3326,
        3478,
        3966,
        4828,
        5289,
        5441,
        5615,
        6156,
        6504,
        6739,
        6926,
        7387,
        8153,
        8745,
        8949,
        9959,
        10328,
        10572,
        11308,
        11309
      ],
      "item_purchases": [
        {
          "type": "ITEM_PURCHASED",
          "timestamp": 5147,
          "itemId": 2003
        },
        {
          "type": "ITEM_PURCHASED",
          "timestamp": 5281,
          "itemId": 2003
        },
        {
          "type": "ITEM_PURCHASED",
          "timestamp": 5481,
          "itemId": 3340
        },
        {
          "type": "ITEM_DESTROYED",
          "timestamp": 198061,
          "itemId": 2003
        },
        {
          "type": "ITEM_DESTROYED",
          "timestamp": 199297,
          "itemId": 2003
        },
        {
          "type": "ITEM_PURCHASED",
          "timestamp": 217059,
          "itemId": 1001
        },
        {
          "type": "ITEM_PURCHASED",
          "timestamp": 231000,
          "itemId": 2022
        },
        {
          "type": "ITEM_PURCHASED",
          "timestamp": 231968,
          "itemId": 2055
        },
        {
          "type": "ITEM_DESTROYED",
          "timestamp": 282836,
          "itemId": 2055
        },
        {
          "type": "ITEM_PURCHASED",
          "timestamp": 360227,
          "itemId": 1052
        },
        {
          "type": "ITEM_PURCHASED",
          "timestamp": 368876,
          "itemId": 2003
        },
        {
          "type": "ITEM_DESTROYED",
          "timestamp": 466425,
          "itemId": 3865
        },
        {
          "type": "ITEM_DESTROYED",
          "timestamp": 496055,
          "itemId": 1052
        },
        {
          "type": "ITEM_PURCHASED",
          "timestamp": 496055,
          "itemId": 3916
        },
        {
          "type": "ITEM_DESTROYED",
          "timestamp": 539878,
          "itemId": 2003
        },
        {
          "type": "ITEM_PURCHASED",
          "timestamp": 574001,
          "itemId": 1027
        },
        {
          "type": "ITEM_DESTROYED",
          "timestamp": 577107,
          "itemId": 3340
        },
        {
          "type": "ITEM_PURCHASED",
          "timestamp": 577107,
          "itemId": 3364
        },
        {
          "type": "ITEM_PURCHASED",
          "timestamp": 659890,
          "itemId": 1052
        },
        {
          "type": "ITEM_DESTROYED",
          "timestamp": 762925,
          "itemId": 3866
        },
        {
          "type": "ITEM_DESTROYED",
          "timestamp": 764695,
          "itemId": 3867
        },
        {
          "type": "ITEM_DESTROYED",
          "timestamp": 766132,
          "itemId": 1052
        },
        {
          "type": "ITEM_DESTROYED",
          "timestamp": 766132,
          "itemId": 1027
        },
        {
          "type": "ITEM_DESTROYED",
          "timestamp": 766132,
          "itemId": 2022
        },
        {
          "type": "ITEM_PURCHASED",
          "timestamp": 766132,
          "itemId": 3802
        },
        {
          "type": "ITEM_PURCHASED",
          "timestamp": 782227,
          "itemId": 1052
        },
        {
          "type": "ITEM_DESTROYED",
          "timestamp": 870110,
          "itemId": 1052
        },
        {
          "type": "ITEM_PURCHASED",
          "timestamp": 870110,
          "itemId": 2508
        },
        {
          "type": "ITEM_DESTROYED",
          "timestamp": 1037194,
          "itemId": 1001
        },
        {
          "type": "ITEM_PURCHASED",
          "timestamp": 1037194,
          "itemId": 3020
        },
        {
          "type": "ITEM_DESTROYED",
          "timestamp": 1039399,
          "itemId": 3802
        },
        {
          "type": "ITEM_DESTROYED",
          "timestamp": 1039399,
          "itemId": 2508
        },
        {
          "type": "ITEM_PURCHASED",
          "timestamp": 1039399,
          "itemId": 2503
        },
        {
          "type": "ITEM_PURCHASED",
          "timestamp": 1104298,
          "itemId": 2055
        },
        {
          "type": "ITEM_PURCHASED",
          "timestamp": 1177592,
          "itemId": 1052
        },
        {
          "type": "ITEM_DESTROYED",
          "timestamp": 1212925,
          "itemId": 1052
        },
        {
          "type": "ITEM_PURCHASED",
          "timestamp": 1212925,
          "itemId": 2508
        },
        {
          "type": "ITEM_DESTROYED",
          "timestamp": 1362809,
          "itemId": 2055
        },
        {
          "type": "ITEM_DESTROYED",
          "timestamp": 1517687,
          "itemId": 2508
        },
        {
          "type": "ITEM_PURCHASED",
          "timestamp": 1517687,
          "itemId": 6653
        },
        {
          "type": "ITEM_PURCHASED",
          "timestamp": 1518790,
          "itemId": 2055
        },
        {
          "type": "ITEM_SOLD",
          "timestamp": 1658370,
          "itemId": 2055
        },
        {
          "type": "ITEM_PURCHASED",
          "timestamp": 1662532,
          "itemId": 1026
        },
        {
          "type": "ITEM_DESTROYED",
          "timestamp": 1835861,
          "itemId": 3916
        },
        {
          "type": "ITEM_DESTROYED",
          "timestamp": 1835861,
          "itemId": 1026
        },
        {
          "type": "ITEM_PURCHASED",
          "timestamp": 1835861,
          "itemId": 3165
        },
        {
          "type": "ITEM_DESTROYED",
          "timestamp": 1838065,
          "itemId": 1026
        },
        {
          "type": "ITEM_PURCHASED",
          "timestamp": 1838065,
          "itemId": 3116
        }
      ],
      "final_items": [
        2503,
        3116,
        3871,
        6653,
        3916,
        3020,
        3364
      ]
    },
    {
      "participantId": 6,
      "championName": "Warwick",
      "teamId": 200,
      "win": false,
      "lane": "TOP",
      "gold_curve": [
        500,
        500,
        618,
        846,
        1101,
        1547,
        1774,
        1952,
        2455,
        2682,
        2985,
        3248,
        3391,
        3707,
        3990,
        4163,
        4847,
        5140,
        5263,
        6120,
        6707,
        6920,
        7147,
        7549,
        7853,
        8233,
        8369,
        8870,
        9017,
        9376,
        9688,
        10015,
        10016
      ],
      "item_purchases": [
        {
          "type": "ITEM_PURCHASED",
          "timestamp": 17907,
          "itemId": 1054
        },
        {
          "type": "ITEM_PURCHASED",
          "timestamp": 17907,
          "itemId": 2003
        },
        {
          "type": "ITEM_PURCHASED",
          "timestamp": 19042,
          "itemId": 3340
        },
        {
          "type": "ITEM_DESTROYED",
          "timestamp": 218262,
          "itemId": 2003
        },
        {
          "type": "ITEM_PURCHASED",
          "timestamp": 365270,
          "itemId": 3077
        },
        {
          "type": "ITEM_PURCHASED",
          "timestamp": 368442,
          "itemId": 2003
        },
        {
          "type": "ITEM_DESTROYED",
          "timestamp": 423416,
          "itemId": 2003
        },
        {
          "type": "ITEM_PURCHASED",
          "timestamp": 495754,
          "itemId": 1028
        },
        {
          "type": "ITEM_PURCHASED",
          "timestamp": 496189,
          "itemId": 1036
        },
        {
          "type": "ITEM_DESTROYED",
          "timestamp": 620894,
          "itemId": 1028
        },
        {
          "type": "ITEM_DESTROYED",
          "timestamp": 620894,
          "itemId": 1036
        },
        {
          "type": "ITEM_PURCHASED",
          "timestamp": 620894,
          "itemId": 3044
        },
        {
          "type": "ITEM_DESTROYED",
          "timestamp": 849908,
          "itemId": 3077
        },
        {
          "type": "ITEM_DESTROYED",
          "timestamp": 849908,
          "itemId": 3044
        },
        {
          "type": "ITEM_PURCHASED",
          "timestamp": 849908,
          "itemId": 6631
        },
        {
          "type": "ITEM_PURCHASED",
          "timestamp": 878026,
          "itemId": 1042
        },
        {
          "type": "ITEM_SOLD",
          "timestamp": 1027688,
          "itemId": 1054
        },
        {
          "type": "ITEM_PURCHASED",
          "timestamp": 1030394,
          "itemId": 3047
        },
        {
          "type": "ITEM_PURCHASED",
          "timestamp": 1186378,
          "itemId": 1037
        },
        {
          "type": "ITEM_DESTROYED",
          "timestamp": 1187247,
          "itemId": 1042
        },
        {
          "type": "ITEM_PURCHASED",
          "timestamp": 1187247,
          "itemId": 1043
        },
        {
          "type": "ITEM_PURCHASED",
          "timestamp": 1189680,
          "itemId": 1053
        },
        {
          "type": "ITEM_DESTROYED",
          "timestamp": 1190849,
          "itemId": 1042
        },
        {
          "type": "ITEM_PURCHASED",
          "timestamp": 1190849,
          "itemId": 1043
        },
        {
          "type": "ITEM_DESTROYED",
          "timestamp": 1511355,
          "itemId": 1053
        },
        {
          "type": "ITEM_DESTROYED",
          "timestamp": 1511355,
          "itemId": 1043
        },
        {
          "type": "ITEM_PURCHASED",
          "timestamp": 1511355,
          "itemId": 3153
        },
        {
          "type": "ITEM_PURCHASED",
          "timestamp": 1628768,
          "itemId": 1028
        },
        {
          "type": "ITEM_PURCHASED",
          "timestamp": 1629036,
          "itemId": 1028
        },
        {
          "type": "ITEM_PURCHASED",
          "timestamp": 1831483,
          "itemId": 1037
        }
      ],
      "final_items": [
        3047,
        6631,
        3153,
        1028,
        1028,
        1037,
        3340
      ]
    },
    {
      "participantId": 7,
      "championName": "MonkeyKing",
      "teamId": 200,
      "win": false,
      "lane": "JUNGLE",
      "gold_curve": [
        500,
        510,
        699,
        1081,
        1723,
        2006,
        2313,
        2640,
        2762,
        3191,
        3818,
        4211,
        4462,
        4659,
        5279,
        5653,
        6270,
        7047,
        7839,
        8095,
        8839,
        9174,
        10088,
        10381,
        10503,
        10625,
        10753,
        11479,
        12014,
        12347,
        12469,
        12890,
        12891
      ],
      "item_purchases": [
        {
          "type": "ITEM_PURCHASED",
          "timestamp": 6517,
          "itemId": 1102
        },
        {
          "type": "ITEM_PURCHASED",
          "timestamp": 6884,
          "itemId": 2003
        },
        {
          "type": "ITEM_PURCHASED",
          "timestamp": 11861,
          "itemId": 3364
        },
        {
          "type": "ITEM_DESTROYED",
          "timestamp": 232536,
          "itemId": 2003
        },
        {
          "type": "ITEM_PURCHASED",
          "timestamp": 445016,
          "itemId": 3051
        },
        {
          "type": "ITEM_PURCHASED",
          "timestamp": 445083,
          "itemId": 3057
        },
        {
          "type": "ITEM_DESTROYED",
          "timestamp": 673138,
          "itemId": 3057
        },
        {
          "type": "ITEM_DESTROYED",
          "timestamp": 673138,
          "itemId": 3051
        },
        {
          "type": "ITEM_PURCHASED",
          "timestamp": 673138,
          "itemId": 3078
        },
        {
          "type": "ITEM_PURCHASED",
          "timestamp": 675543,
          "itemId": 1029
        },
        {
          "type": "ITEM_DESTROYED",
          "timestamp": 896318,
          "itemId": 1102
        },
        {
          "type": "ITEM_PURCHASED",
          "timestamp": 928287,
          "itemId": 2021
        },
        {
          "type": "ITEM_PURCHASED",
          "timestamp": 928354,
          "itemId": 1028
        },
        {
          "type": "ITEM_PURCHASED",
          "timestamp": 928420,
          "itemId": 1036
        },
        {
          "type": "ITEM_DESTROYED",
          "timestamp": 1048027,
          "itemId": 3364
        },
        {
          "type": "ITEM_DESTROYED",
          "timestamp": 1094443,
          "itemId": 2021
        },
        {
          "type": "ITEM_DESTROYED",
          "timestamp": 1094443,
          "itemId": 1036
        },
        {
          "type": "ITEM_DESTROYED",
          "timestamp": 1094443,
          "itemId": 1028
        },
        {
          "type": "ITEM_PURCHASED",
          "timestamp": 1094443,
          "itemId": 6610
        },
        {
          "type": "ITEM_DESTROYED",
          "timestamp": 1095412,
          "itemId": 2422
        },
        {
          "type": "ITEM_DESTROYED",
          "timestamp": 1095412,
          "itemId": 1029
        },
        {
          "type": "ITEM_PURCHASED",
          "timestamp": 1095412,
          "itemId": 3047
        },
        {
          "type": "ITEM_DESTROYED",
          "timestamp": 1125072,
          "itemId": 3513
        },
        {
          "type": "ITEM_PURCHASED",
          "timestamp": 1355124,
          "itemId": 3044
        },
        {
          "type": "ITEM_PURCHASED",
          "timestamp": 1355190,
          "itemId": 1037
        },
        {
          "type": "ITEM_PURCHASED",
          "timestamp": 1355257,
          "itemId": 1028
        },
        {
          "type": "ITEM_DESTROYED",
          "timestamp": 1357996,
          "itemId": 3047
        },
        {
          "type": "ITEM_PURCHASED",
          "timestamp": 1357996,
          "itemId": 3174
        },
        {
          "type": "ITEM_PURCHASED",
          "timestamp": 1360401,
          "itemId": 3067
        },
        {
          "type": "ITEM_PURCHASED",
          "timestamp": 1597877,
          "itemId": 1037
        },
        {
          "type": "ITEM_DESTROYED",
          "timestamp": 1650186,
          "itemId": 3044
        },
        {
          "type": "ITEM_DESTROYED",
          "timestamp": 1650186,
          "itemId": 3067
        },
        {
          "type": "ITEM_DESTROYED",
          "timestamp": 1650186,
          "itemId": 1037
        },
        {
          "type": "ITEM_PURCHASED",
          "timestamp": 1650186,
          "itemId": 3071
        },
        {
          "type": "ITEM_PURCHASED",
          "timestamp": 1652157,
          "itemId": 1036
        },
        {
          "type": "ITEM_PURCHASED",
          "timestamp": 1677516,
          "itemId": 1029
        }
      ],
      "final_items": [
        3174,
        3078,
        3071,
        6610,
        1036,
        1029,
        3364
      ]
    },
    {
      "participantId": 8,
      "championName": "Kassadin",
      "teamId": 200,
      "win": false,
      "lane": "MIDDLE",
      "gold_curve": [
        500,
        500,
        932,
        1139,
        1506,
        1664,
        1968,
        2362,
        2683,
        2994,
        3311,
        3637,
        4003,
        4304,
        4866,
        5553,
        6114,
        6471,
        6720,
        7552,
        8062,
        8185,
        8307,
        8605,
        9108,
        9666,
        9788,
        10192,
        11327,
        12068,
        12190,
        12312,
        12313
      ],
      "item_purchases": [
        {
          "type": "ITEM_PURCHASED",
          "timestamp": 13164,
          "itemId": 1054
        },
        {
          "type": "ITEM_PURCHASED",
          "timestamp": 13164,
          "itemId": 2003
        },
        {
          "type": "ITEM_PURCHASED",
          "timestamp": 13731,
          "itemId": 3340
        },
        {
          "type": "ITEM_DESTROYED",
          "timestamp": 70074,
          "itemId": 2003
        },
        {
          "type": "ITEM_PURCHASED",
          "timestamp": 115308,
          "itemId": 3070
        },
        {
          "type": "ITEM_PURCHASED",
          "timestamp": 273356,
          "itemId": 1028
        },
        {
          "type": "ITEM_PURCHASED",
          "timestamp": 418253,
          "itemId": 1026
        },
        {
          "type": "ITEM_PURCHASED",
          "timestamp": 420444,
          "itemId": 2055
        },
        {
          "type": "ITEM_PURCHASED",
          "timestamp": 420711,
          "itemId": 2003
        },
        {
          "type": "ITEM_PURCHASED",
          "timestamp": 420878,
          "itemId": 2003
        },
        {
          "type": "ITEM_DESTROYED",
          "timestamp": 585257,
          "itemId": 2003
        },
        {
          "type": "ITEM_DESTROYED",
          "timestamp": 587845,
          "itemId": 2003
        },
        {
          "type": "ITEM_DESTROYED",
          "timestamp": 631350,
          "itemId": 1028
        },
        {
          "type": "ITEM_PURCHASED",
          "timestamp": 631350,
          "itemId": 3803
        },
        {
          "type": "ITEM_PURCHASED",
          "timestamp": 633588,
          "itemId": 2003
        },
        {
          "type": "ITEM_PURCHASED",
          "timestamp": 633721,
          "itemId": 2003
        },
        {
          "type": "ITEM_DESTROYED",
          "timestamp": 673973,
          "itemId": 2003
        },
        {
          "type": "ITEM_DESTROYED",
          "timestamp": 686143,
          "itemId": 2003
        },
        {
          "type": "ITEM_DESTROYED",
          "timestamp": 738383,
          "itemId": 1026
        },
        {
          "type": "ITEM_DESTROYED",
          "timestamp": 738383,
          "itemId": 3803
        },
        {
          "type": "ITEM_PURCHASED",
          "timestamp": 738383,
          "itemId": 6657
        },
        {
          "type": "ITEM_PURCHASED",
          "timestamp": 739318,
          "itemId": 1052
        },
        {
          "type": "ITEM_PURCHASED",
          "timestamp": 741855,
          "itemId": 1052
        },
        {
          "type": "ITEM_DESTROYED",
          "timestamp": 923811,
          "itemId": 1052
        },
        {
          "type": "ITEM_PURCHASED",
          "timestamp": 923811,
          "itemId": 3802
        },
        {
          "type": "ITEM_PURCHASED",
          "timestamp": 924312,
          "itemId": 3108
        },
        {
          "type": "ITEM_SOLD",
          "timestamp": 926784,
          "itemId": 1054
        },
        {
          "type": "ITEM_DESTROYED",
          "timestamp": 995451,
          "itemId": 2055
        },
        {
          "type": "ITEM_DESTROYED",
          "timestamp": 1030294,
          "itemId": 3070
        },
        {
          "type": "ITEM_DESTROYED",
          "timestamp": 1030294,
          "itemId": 3802
        },
        {
          "type": "ITEM_DESTROYED",
          "timestamp": 1030294,
          "itemId": 3108
        },
        {
          "type": "ITEM_PURCHASED",
          "timestamp": 1030294,
          "itemId": 3003
        },
        {
          "type": "ITEM_DESTROYED",
          "timestamp": 1073428,
          "itemId": 3003
        },
        {
          "type": "ITEM_PURCHASED",
          "timestamp": 1128045,
          "itemId": 3020
        },
        {
          "type": "ITEM_PURCHASED",
          "timestamp": 1131521,
          "itemId": 2055
        },
        {
          "type": "ITEM_PURCHASED",
          "timestamp": 1204410,
          "itemId": 1052
        },
        {
          "type": "ITEM_DESTROYED",
          "timestamp": 1225584,
          "itemId": 2055
        },
        {
          "type": "ITEM_PURCHASED",
          "timestamp": 1256398,
          "itemId": 1027
        },
        {
          "type": "ITEM_DESTROYED",
          "timestamp": 1425539,
          "itemId": 1052
        },
        {
          "type": "ITEM_DESTROYED",
          "timestamp": 1425539,
          "itemId": 1027
        },
        {
          "type": "ITEM_PURCHASED",
          "timestamp": 1425539,
          "itemId": 3802
        },
        {
          "type": "ITEM_PURCHASED",
          "timestamp": 1426942,
          "itemId": 2055
        },
        {
          "type": "ITEM_SOLD",
          "timestamp": 1510854,
          "itemId": 1054
        },
        {
          "type": "ITEM_PURCHASED",
          "timestamp": 1511856,
          "itemId": 1026
        },
        {
          "type": "ITEM_DESTROYED",
          "timestamp": 1601718,
          "itemId": 2055
        },
        {
          "type": "ITEM_DESTROYED",
          "timestamp": 1665137,
          "itemId": 3802
        },
        {
          "type": "ITEM_DESTROYED",
          "timestamp": 1665137,
          "itemId": 1026
        },
        {
          "type": "ITEM_PURCHASED",
          "timestamp": 1665137,
          "itemId": 3118
        },
        {
          "type": "ITEM_DESTROYED",
          "timestamp": 1666139,
          "itemId": 3020
        },
        {
          "type": "ITEM_PURCHASED",
          "timestamp": 1666139,
          "itemId": 3175
        },
        {
          "type": "ITEM_PURCHASED",
          "timestamp": 1764480,
          "itemId": 1058
        }
      ],
      "final_items": [
        3118,
        3040,
        6657,
        3175,
        1058,
        0,
        3340
      ]
    },
    {
      "participantId": 9,
      "championName": "Sivir",
      "teamId": 200,
      "win": false,
      "lane": "BOTTOM",
      "gold_curve": [
        500,
        505,
        609,
        837,
        1713,
        1913,
        2231,
        2555,
        2834,
        3288,
        3668,
        3994,
        4792,
        5214,
        5610,
        6824,
        7110,
        8044,
        8424,
        8979,
        9892,
        10115,
        10655,
        10988,
        11358,
        11537,
        11958,
        13144,
        13292,
        14006,
        14744,
        16972,
        16973
      ],
      "item_purchases": [
        {
          "type": "ITEM_PURCHASED",
          "timestamp": 5314,
          "itemId": 1055
        },
        {
          "type": "ITEM_PURCHASED",
          "timestamp": 5314,
          "itemId": 2003
        },
        {
          "type": "ITEM_PURCHASED",
          "timestamp": 6416,
          "itemId": 3340
        },
        {
          "type": "ITEM_DESTROYED",
          "timestamp": 152552,
          "itemId": 2003
        },
        {
          "type": "ITEM_DESTROYED",
          "timestamp": 180139,
          "itemId": 2010
        },
        {
          "type": "ITEM_PURCHASED",
          "timestamp": 234273,
          "itemId": 1037
        },
        {
          "type": "ITEM_PURCHASED",
          "timestamp": 238149,
          "itemId": 1036
        },
        {
          "type": "ITEM_PURCHASED",
          "timestamp": 238382,
          "itemId": 1036
        },
        {
          "type": "ITEM_DESTROYED",
          "timestamp": 239351,
          "itemId": 1036
        },
        {
          "type": "ITEM_DESTROYED",
          "timestamp": 239351,
          "itemId": 1036
        },
        {
          "type": "ITEM_PURCHASED",
          "timestamp": 239351,
          "itemId": 3133
        },
        {
          "type": "ITEM_DESTROYED",
          "timestamp": 275829,
          "itemId": 2010
        },
        {
          "type": "ITEM_DESTROYED",
          "timestamp": 361295,
          "itemId": 2010
        },
        {
          "type": "ITEM_PURCHASED",
          "timestamp": 430999,
          "itemId": 1037
        },
        {
          "type": "ITEM_PURCHASED",
          "timestamp": 434340,
          "itemId": 2031
        },
        {
          "type": "ITEM_DESTROYED",
          "timestamp": 597531,
          "itemId": 1037
        },
        {
          "type": "ITEM_DESTROYED",
          "timestamp": 597531,
          "itemId": 3133
        },
        {
          "type": "ITEM_PURCHASED",
          "timestamp": 597531,
          "itemId": 3508
        },
        {
          "type": "ITEM_PURCHASED",
          "timestamp": 773304,
          "itemId": 1038
        },
        {
          "type": "ITEM_DESTROYED",
          "timestamp": 936591,
          "itemId": 1038
        },
        {
          "type": "ITEM_PURCHASED",
          "timestamp": 936591,
          "itemId": 3031
        },
        {
          "type": "ITEM_DESTROYED",
          "timestamp": 1020674,
          "itemId": 2422
        },
        {
          "type": "ITEM_PURCHASED",
          "timestamp": 1020674,
          "itemId": 3006
        },
        {
          "type": "ITEM_PURCHASED",
          "timestamp": 1045645,
          "itemId": 1042
        },
        {
          "type": "ITEM_DESTROYED",
          "timestamp": 1205279,
          "itemId": 1042
        },
        {
          "type": "ITEM_PURCHASED",
          "timestamp": 1205279,
          "itemId": 3086
        },
        {
          "type": "ITEM_DESTROYED",
          "timestamp": 1206481,
          "itemId": 3006
        },
        {
          "type": "ITEM_PURCHASED",
          "timestamp": 1206481,
          "itemId": 3172
        },
        {
          "type": "ITEM_SOLD",
          "timestamp": 1331612,
          "itemId": 1055
        },
        {
          "type": "ITEM_PURCHASED",
          "timestamp": 1332547,
          "itemId": 1042
        },
        {
          "type": "ITEM_DESTROYED",
          "timestamp": 1407883,
          "itemId": 1042
        },
        {
          "type": "ITEM_DESTROYED",
          "timestamp": 1407883,
          "itemId": 3086
        },
        {
          "type": "ITEM_PURCHASED",
          "timestamp": 1407883,
          "itemId": 6675
        },
        {
          "type": "ITEM_PURCHASED",
          "timestamp": 1410355,
          "itemId": 1036
        },
        {
          "type": "ITEM_DESTROYED",
          "timestamp": 1631984,
          "itemId": 1036
        },
        {
          "type": "ITEM_PURCHASED",
          "timestamp": 1631984,
          "itemId": 3035
        },
        {
          "type": "ITEM_DESTROYED",
          "timestamp": 1772898,
          "itemId": 3035
        },
        {
          "type": "ITEM_PURCHASED",
          "timestamp": 1772898,
          "itemId": 3036
        },
        {
          "type": "ITEM_SOLD",
          "timestamp": 1847039,
          "itemId": 2031
        }
      ],
      "final_items": [
        0,
        3031,
        3508,
        6675,
        3172,
        3036,
        3340
      ]
    },
    {
      "participantId": 10,
      "championName": "Pantheon",
      "teamId": 200,
      "win": false,
      "lane": "UTILITY",
      "gold_curve": [
        500,
        500,
        620,
        804,
        1304,
        1553,
        1757,
        1935,
        2170,
        2542,
        2873,
        3066,
        3830,
        4026,
        4734,
        5290,
        5674,
        6353,
        6506,
        7207,
        7789,
        8183,
        8588,
        8796,
        9063,
        9439,
        10518,
        10931,
        11276,
        11428,
        11580,
        11978,
        11979
      ],
      "item_purchases": [
        {
          "type": "ITEM_PURCHASED",
          "timestamp": 10291,
          "itemId": 2003
        },
        {
          "type": "ITEM_PURCHASED",
          "timestamp": 10425,
          "itemId": 2003
        },
        {
          "type": "ITEM_PURCHASED",
          "timestamp": 10992,
          "itemId": 3340
        },
        {
          "type": "ITEM_DESTROYED",
          "timestamp": 143013,
          "itemId": 2003
        },
        {
          "type": "ITEM_DESTROYED",
          "timestamp": 180841,
          "itemId": 2003
        },
        {
          "type": "ITEM_PURCHASED",
          "timestamp": 208639,
          "itemId": 1001
        },
        {
          "type": "ITEM_PURCHASED",
          "timestamp": 210242,
          "itemId": 1028
        },
        {
          "type": "ITEM_PURCHASED",
          "timestamp": 217193,
          "itemId": 2003
        },
        {
          "type": "ITEM_DESTROYED",
          "timestamp": 283704,
          "itemId": 2003
        },
        {
          "type": "ITEM_PURCHASED",
          "timestamp": 409568,
          "itemId": 1036
        },
        {
          "type": "ITEM_PURCHASED",
          "timestamp": 410103,
          "itemId": 2022
        },
        {
          "type": "ITEM_PURCHASED",
          "timestamp": 411673,
          "itemId": 2003
        },
        {
          "type": "ITEM_DESTROYED",
          "timestamp": 473372,
          "itemId": 3865
        },
        {
          "type": "ITEM_DESTROYED",
          "timestamp": 542047,
          "itemId": 2003
        },
        {
          "type": "ITEM_DESTROYED",
          "timestamp": 564322,
          "itemId": 1036
        },
        {
          "type": "ITEM_DESTROYED",
          "timestamp": 564322,
          "itemId": 1028
        },
        {
          "type": "ITEM_PURCHASED",
          "timestamp": 564322,
          "itemId": 2021
        },
        {
          "type": "ITEM_PURCHASED",
          "timestamp": 564423,
          "itemId": 1028
        },
        {
          "type": "ITEM_PURCHASED",
          "timestamp": 565892,
          "itemId": 2055
        },
        {
          "type": "ITEM_DESTROYED",
          "timestamp": 566360,
          "itemId": 3340
        },
        {
          "type": "ITEM_PURCHASED",
          "timestamp": 566360,
          "itemId": 3364
        },
        {
          "type": "ITEM_DESTROYED",
          "timestamp": 620260,
          "itemId": 2055
        },
        {
          "type": "ITEM_DESTROYED",
          "timestamp": 763760,
          "itemId": 2022
        },
        {
          "type": "ITEM_PURCHASED",
          "timestamp": 763760,
          "itemId": 3133
        },
        {
          "type": "ITEM_PURCHASED",
          "timestamp": 772369,
          "itemId": 2055
        },
        {
          "type": "ITEM_DESTROYED",
          "timestamp": 801685,
          "itemId": 3866
        },
        {
          "type": "ITEM_DESTROYED",
          "timestamp": 803122,
          "itemId": 3867
        },
        {
          "type": "ITEM_DESTROYED",
          "timestamp": 862833,
          "itemId": 2021
        },
        {
          "type": "ITEM_DESTROYED",
          "timestamp": 862833,
          "itemId": 3133
        },
        {
          "type": "ITEM_DESTROYED",
          "timestamp": 862833,
          "itemId": 1028
        },
        {
          "type": "ITEM_PURCHASED",
          "timestamp": 862833,
          "itemId": 6610
        },
        {
          "type": "ITEM_DESTROYED",
          "timestamp": 868440,
          "itemId": 1001
        },
        {
          "type": "ITEM_PURCHASED",
          "timestamp": 868440,
          "itemId": 3009
        },
        {
          "type": "ITEM_PURCHASED",
          "timestamp": 872014,
          "itemId": 2022
        },
        {
          "type": "ITEM_PURCHASED",
          "timestamp": 927986,
          "itemId": 1028
        },
        {
          "type": "ITEM_DESTROYED",
          "timestamp": 1052913,
          "itemId": 1028
        },
        {
          "type": "ITEM_PURCHASED",
          "timestamp": 1052913,
          "itemId": 3044
        },
        {
          "type": "ITEM_DESTROYED",
          "timestamp": 1160932,
          "itemId": 2055
        },
        {
          "type": "ITEM_PURCHASED",
          "timestamp": 1170752,
          "itemId": 1037
        },
        {
          "type": "ITEM_DESTROYED",
          "timestamp": 1217334,
          "itemId": 3044
        },
        {
          "type": "ITEM_DESTROYED",
          "timestamp": 1217334,
          "itemId": 2022
        },
        {
          "type": "ITEM_DESTROYED",
          "timestamp": 1217334,
          "itemId": 1037
        },
        {
          "type": "ITEM_PURCHASED",
          "timestamp": 1217334,
          "itemId": 3071
        },
        {
          "type": "ITEM_PURCHASED",
          "timestamp": 1241267,
          "itemId": 2022
        },
        {
          "type": "ITEM_PURCHASED",
          "timestamp": 1293024,
          "itemId": 2055
        },
        {
          "type": "ITEM_DESTROYED",
          "timestamp": 1315771,
          "itemId": 2055
        },
        {
          "type": "ITEM_DESTROYED",
          "timestamp": 1420092,
          "itemId": 2022
        },
        {
          "type": "ITEM_PURCHASED",
          "timestamp": 1420092,
          "itemId": 3133
        },
        {
          "type": "ITEM_PURCHASED",
          "timestamp": 1483967,
          "itemId": 1036
        },
        {
          "type": "ITEM_DESTROYED",
          "timestamp": 1585392,
          "itemId": 1036
        },
        {
          "type": "ITEM_PURCHASED",
          "timestamp": 1585392,
          "itemId": 2019
        },
        {
          "type": "ITEM_DESTROYED",
          "timestamp": 1668644,
          "itemId": 2019
        },
        {
          "type": "ITEM_DESTROYED",
          "timestamp": 1668644,
          "itemId": 3133
        },
        {
          "type": "ITEM_PURCHASED",
          "timestamp": 1668644,
          "itemId": 6333
        },
        {
          "type": "ITEM_PURCHASED",
          "timestamp": 1776205,
          "itemId": 2055
        }
      ],
      "final_items": [
        3877,
        3009,
        6610,
        3071,
        6333,
        2055,
        3364
      ]
    }
  ]
}