{
  "matchId": "EUW1_7664389406",
  "gameDate": "2025-12-30 20:02:32",
  "rank": "IRON I",
  "gameMode": "CLASSIC",
  "gameDuration": 2338,
  "timestamps_minutes": [
    0.0,
    1.0005333333333333,
    2.0008166666666667,
    3.00255,
    4.002966666666667,
    5.003383333333334,
    6.003916666666667,
    7.003983333333333,
    8.004516666666667,
    9.004583333333333,
    10.004583333333333,
    11.00475,
    12.004883333333334,
    13.005116666666666,
    14.005483333333334,
    15.00595,
    16.006033333333335,
    17.00645,
    18.006716666666666,
    19.007233333333332,
    20.007483333333333,
    21.007766666666665,
    22.008016666666666,
    23.0084,
    24.008883333333333,
    25.008916666666668,
    26.009316666666667,
    27.009816666666666,
    28.01095,
    29.011466666666667,
    30.011683333333334,
    31.01175,
    32.01201666666667,
    33.0122,
    34.0127,
    35.01273333333334,
    36.012766666666664,
    37.01291666666667,
    38.01303333333333,
    38.9772
  ],
  "participants": [
    {
      "participantId": 1,
      "championName": "Volibear",
      "teamId": 100,
      "win": true,
      "lane": "TOP",
      "gold_curve": [
        500,
        500,
        841,
        1097,
        1659,
        1845,
        2389,
        2671,
        2914,
        3107,
        3454,
        3788,
        4015,
        4281,
        4502,
        4753,
        5068,
        5410,
        5643,
        5990,
        6221,
        7486,
        8331,
        8566,
        9556,
        9943,
        10260,
        10382,
        10742,
        10982,
        11171,
        11683,
        12426,
        12894,
        13539,
        13781,
        14223,
        14471,
        14695,
        14962
      ],
      "item_purchases": [
        {
          "type": "ITEM_PURCHASED",
          "timestamp": 11046,
          "itemId": 3070
        },
        {
          "type": "ITEM_PURCHASED",
          "timestamp": 11614,
          "itemId": 2003
        },
        {
          "type": "ITEM_PURCHASED",
          "timestamp": 11915,
          "itemId": 2003
        },
        {
          "type": "ITEM_DESTROYED",
          "timestamp": 110220,
          "itemId": 2003
        },
        {
          "type": "ITEM_DESTROYED",
          "timestamp": 148683,
          "itemId": 2003
        },
        {
          "type": "ITEM_PURCHASED",
          "timestamp": 167535,
          "itemId": 1001
        },
        {
          "type": "ITEM_PURCHASED",
          "timestamp": 167602,
          "itemId": 2022
        },
        {
          "type": "ITEM_DESTROYED",
          "timestamp": 244556,
          "itemId": 1001
        },
        {
          "type": "ITEM_DESTROYED",
          "timestamp": 244556,
          "itemId": 2022
        },
        {
          "type": "ITEM_PURCHASED",
          "timestamp": 244556,
          "itemId": 3158
        },
        {
          "type": "ITEM_PURCHASED",
          "timestamp": 247897,
          "itemId": 2022
        },
        {
          "type": "ITEM_PURCHASED",
          "timestamp": 430129,
          "itemId": 1011
        },
        {
          "type": "ITEM_DESTROYED",
          "timestamp": 436542,
          "itemId": 2022
        },
        {
          "type": "ITEM_PURCHASED",
          "timestamp": 436542,
          "itemId": 3067
        },
        {
          "type": "ITEM_PURCHASED",
          "timestamp": 437344,
          "itemId": 1028
        },
        {
          "type": "ITEM_DESTROYED",
          "timestamp": 538336,
          "itemId": 1028
        },
        {
          "type": "ITEM_PURCHASED",
          "timestamp": 538336,
          "itemId": 1011
        },
        {
          "type": "ITEM_DESTROYED",
          "timestamp": 666514,
          "itemId": 3070
        },
        {
          "type": "ITEM_DESTROYED",
          "timestamp": 666514,
          "itemId": 1011
        },
        {
          "type": "ITEM_DESTROYED",
          "timestamp": 666514,
          "itemId": 3067
        },
        {
          "type": "ITEM_PURCHASED",
          "timestamp": 666514,
          "itemId": 3119
        },
        {
          "type": "ITEM_PURCHASED",
          "timestamp": 668317,
          "itemId": 1028
        },
        {
          "type": "ITEM_PURCHASED",
          "timestamp": 789071,
          "itemId": 1033
        },
        {
          "type": "ITEM_DESTROYED",
          "timestamp": 968099,
          "itemId": 1028
        },
        {
          "type": "ITEM_DESTROYED",
          "timestamp": 968099,
          "itemId": 1033
        },
        {
          "type": "ITEM_PURCHASED",
          "timestamp": 968099,
          "itemId": 3211
        },
        {
          "type": "ITEM_PURCHASED",
          "timestamp": 968166,
          "itemId": 1028
        },
        {
          "type": "ITEM_DESTROYED",
          "timestamp": 990468,
          "itemId": 3119
        },
        {
          "type": "ITEM_DESTROYED",
          "timestamp": 1135432,
          "itemId": 3340
        },
        {
          "type": "ITEM_DESTROYED",
          "timestamp": 1169303,
          "itemId": 3211
        },
        {
          "type": "ITEM_DESTROYED",
          "timestamp": 1169303,
          "itemId": 1028
        },
        {
          "type": "ITEM_PURCHASED",
          "timestamp": 1169303,
          "itemId": 3065
        },
        {
          "type": "ITEM_PURCHASED",
          "timestamp": 1347330,
          "itemId": 3086
        },
        {
          "type": "ITEM_PURCHASED",
          "timestamp": 1347430,
          "itemId": 1042
        },
        {
          "type": "ITEM_PURCHASED",
          "timestamp": 1347530,
          "itemId": 1042
        },
        {
          "type": "ITEM_DESTROYED",
          "timestamp": 1392301,
          "itemId": 3513
        },
        {
          "type": "ITEM_DESTROYED",
          "timestamp": 1447790,
          "itemId": 1042
        },
        {
          "type": "ITEM_DESTROYED",
          "timestamp": 1447790,
          "itemId": 3086
        },
        {
          "type": "ITEM_DESTROYED",
          "timestamp": 1447790,
          "itemId": 1042
        },
        {
          "type": "ITEM_PURCHASED",
          "timestamp": 1447790,
          "itemId": 6675
        },
        {
          "type": "ITEM_PURCHASED",
          "timestamp": 1455643,
          "itemId": 3082
        },
        {
          "type": "ITEM_PURCHASED",
          "timestamp": 1561679,
          "itemId": 2022
        },
        {
          "type": "ITEM_PURCHASED",
          "timestamp": 1565891,
          "itemId": 2022
        },
        {
          "type": "ITEM_PURCHASED",
          "timestamp": 1574705,
          "itemId": 2022
        },
        {
          "type": "ITEM_DESTROYED",
          "timestamp": 1941933,
          "itemId": 3082
        },
        {
          "type": "ITEM_DESTROYED",
          "timestamp": 1941933,
          "itemId": 2022
        },
        {
          "type": "ITEM_PURCHASED",
          "timestamp": 1941933,
          "itemId": 3110
        },
        {
          "type": "ITEM_PURCHASED",
          "timestamp": 1954039,
          "itemId": 1031
        },
        {
          "type": "ITEM_PURCHASED",
          "timestamp": 1959260,
          "itemId": 3057
        },
        {
          "type": "ITEM_DESTROYED",
          "timestamp": 2232080,
          "itemId": 3057
        },
        {
          "type": "ITEM_PURCHASED",
          "timestamp": 2232080,
          "itemId": 6662
        }
      ],
      "final_items": [
        3121,
        3158,
        3065,
        6675,
        3110,
        6662,
        3340
      ]
    },
    {
      "participantId": 2,
      "championName": "Briar",
      "teamId": 100,
      "win": true,
      "lane": "JUNGLE",
      "gold_curve": [
        500,
        500,
        779,
        1091,
        1432,
        1625,
        2083,
        2311,
        2975,
        3192,
        3520,
        3832,
        4435,
        4732,
        5114,
        5237,
        5488,
        6209,
        6552,
        6724,
        7071,
        7194,
        7567,
        7800,
        8208,
        8594,
        9084,
        9206,
        9538,
        9865,
        10174,
        10321,
        10493,
        11259,
        11500,
        11953,
        12635,
        13136,
        13505,
        13917
      ],
      "item_purchases": [
        {
          "type": "ITEM_PURCHASED",
          "timestamp": 6303,
          "itemId": 1102
        },
        {
          "type": "ITEM_PURCHASED",
          "timestamp": 7238,
          "itemId": 3340
        },
        {
          "type": "ITEM_PURCHASED",
          "timestamp": 275047,
          "itemId": 1053
        },
        {
          "type": "ITEM_PURCHASED",
          "timestamp": 508146,
          "itemId": 1037
        },
        {
          "type": "ITEM_PURCHASED",
          "timestamp": 508680,
          "itemId": 1043
        },
        {
          "type": "ITEM_DESTROYED",
          "timestamp": 858758,
          "itemId": 1053
        },
        {
          "type": "ITEM_DESTROYED",
          "timestamp": 858758,
          "itemId": 1043
        },
        {
          "type": "ITEM_DESTROYED",
          "timestamp": 858758,
          "itemId": 1037
        },
        {
          "type": "ITEM_PURCHASED",
          "timestamp": 858758,
          "itemId": 3153
        },
        {
          "type": "ITEM_PURCHASED",
          "timestamp": 868678,
          "itemId": 3047
        },
        {
          "type": "ITEM_PURCHASED",
          "timestamp": 871985,
          "itemId": 2022
        },
        {
          "type": "ITEM_PURCHASED",
          "timestamp": 1106038,
          "itemId": 3044
        },
        {
          "type": "ITEM_PURCHASED",
          "timestamp": 1107244,
          "itemId": 1028
        },
        {
          "type": "ITEM_DESTROYED",
          "timestamp": 1174089,
          "itemId": 1102
        },
        {
          "type": "ITEM_DESTROYED",
          "timestamp": 1214148,
          "itemId": 1028
        },
        {
          "type": "ITEM_DESTROYED",
          "timestamp": 1214148,
          "itemId": 2022
        },
        {
          "type": "ITEM_PURCHASED",
          "timestamp": 1214148,
          "itemId": 3067
        },
        {
          "type": "ITEM_PURCHASED",
          "timestamp": 1336507,
          "itemId": 1036
        },
        {
          "type": "ITEM_PURCHASED",
          "timestamp": 1337476,
          "itemId": 1036
        },
        {
          "type": "ITEM_DESTROYED",
          "timestamp": 1481675,
          "itemId": 3044
        },
        {
          "type": "ITEM_DESTROYED",
          "timestamp": 1481675,
          "itemId": 3067
        },
        {
          "type": "ITEM_PURCHASED",
          "timestamp": 1481675,
          "itemId": 3071
        },
        {
          "type": "ITEM_DESTROYED",
          "timestamp": 1542397,
          "itemId": 1036
        },
        {
          "type": "ITEM_DESTROYED",
          "timestamp": 1542397,
          "itemId": 1036
        },
        {
          "type": "ITEM_PURCHASED",
          "timestamp": 1542397,
          "itemId": 3133
        },
        {
          "type": "ITEM_PURCHASED",
          "timestamp": 1839578,
          "itemId": 2019
        },
        {
          "type": "ITEM_DESTROYED",
          "timestamp": 1968382,
          "itemId": 2019
        },
        {
          "type": "ITEM_DESTROYED",
          "timestamp": 1968382,
          "itemId": 3133
        },
        {
          "type": "ITEM_PURCHASED",
          "timestamp": 1968382,
          "itemId": 6333
        },
        {
          "type": "ITEM_PURCHASED",
          "timestamp": 2053398,
          "itemId": 1036
        },
        {
          "type": "ITEM_PURCHASED",
          "timestamp": 2053965,
          "itemId": 1036
        },
        {
          "type": "ITEM_DESTROYED",
          "timestamp": 2277787,
          "itemId": 1036
        },
        {
          "type": "ITEM_DESTROYED",
          "timestamp": 2277787,
          "itemId": 1036
        },
        {
          "type": "ITEM_PURCHASED",
          "timestamp": 2277787,
          "itemId": 3077
        },
        {
          "type": "ITEM_PURCHASED",
          "timestamp": 2278422,
          "itemId": 2021
        }
      ],
      "final_items": [
        3071,
        3153,
        3047,
        6333,
        3077,
        2021,
        3340
      ]
    },
    {
      "participantId": 3,
      "championName": "Lux",
      "teamId": 100,
      "win": true,
      "lane": "MIDDLE",
      "gold_curve": [
        500,
        500,
        576,
        1062,
        1310,
        1767,
        1981,
        2601,
        3028,
        3421,
        3932,
        4326,
        4822,
        5130,
        5914,
        6041,
        6194,
        6421,
        6804,
        7205,
        7899,
        8655,
        9223,
        9362,
        10098,
        10220,
        10615,
        12489,
        13078,
        13200,
        13918,
        14040,
        14528,
        15892,
        16571,
        16756,
        17607,
        17729,
        18055,
        18356
      ],
      "item_purchases": [
        {
          "type": "ITEM_PURCHASED",
          "timestamp": 12416,
          "itemId": 1056
        },
        {
          "type": "ITEM_PURCHASED",
          "timestamp": 12416,
          "itemId": 2003
        },
        {
          "type": "ITEM_PURCHASED",
          "timestamp": 12416,
          "itemId": 2003
        },
        {
          "type": "ITEM_PURCHASED",
          "timestamp": 13284,
          "itemId": 3340
        },
        {
          "type": "ITEM_DESTROYED",
          "timestamp": 87834,
          "itemId": 2003
        },
        {
          "type": "ITEM_DESTROYED",
          "timestamp": 103338,
          "itemId": 2003
        },
        {
          "type": "ITEM_PURCHASED",
          "timestamp": 174316,
          "itemId": 2022
        },
        {
          "type": "ITEM_PURCHASED",
          "timestamp": 174919,
          "itemId": 1027
        },
        {
          "type": "ITEM_DESTROYED",
          "timestamp": 280363,
          "itemId": 1027
        },
        {
          "type": "ITEM_DESTROYED",
          "timestamp": 280363,
          "itemId": 2022
        },
        {
          "type": "ITEM_PURCHASED",
          "timestamp": 280363,
          "itemId": 3802
        },
        {
          "type": "ITEM_PURCHASED",
          "timestamp": 293472,
          "itemId": 2003
        },
        {
          "type": "ITEM_DESTROYED",
          "timestamp": 328811,
          "itemId": 2003
        },
        {
          "type": "ITEM_PURCHASED",
          "timestamp": 478835,
          "itemId": 3145
        },
        {
          "type": "ITEM_PURCHASED",
          "timestamp": 480542,
          "itemId": 2003
        },
        {
          "type": "ITEM_PURCHASED",
          "timestamp": 480843,
          "itemId": 2003
        },
        {
          "type": "ITEM_DESTROYED",
          "timestamp": 597002,
          "itemId": 2003
        },
        {
          "type": "ITEM_DESTROYED",
          "timestamp": 673779,
          "itemId": 2003
        },
        {
          "type": "ITEM_DESTROYED",
          "timestamp": 688451,
          "itemId": 3802
        },
        {
          "type": "ITEM_DESTROYED",
          "timestamp": 688451,
          "itemId": 3145
        },
        {
          "type": "ITEM_PURCHASED",
          "timestamp": 688451,
          "itemId": 6655
        },
        {
          "type": "ITEM_PURCHASED",
          "timestamp": 689286,
          "itemId": 3020
        },
        {
          "type": "ITEM_PURCHASED",
          "timestamp": 854118,
          "itemId": 1058
        },
        {
          "type": "ITEM_PURCHASED",
          "timestamp": 936825,
          "itemId": 1052
        },
        {
          "type": "ITEM_PURCHASED",
          "timestamp": 1056311,
          "itemId": 1052
        },
        {
          "type": "ITEM_DESTROYED",
          "timestamp": 1088366,
          "itemId": 1052
        },
        {
          "type": "ITEM_DESTROYED",
          "timestamp": 1088366,
          "itemId": 1052
        },
        {
          "type": "ITEM_PURCHASED",
          "timestamp": 1088366,
          "itemId": 3145
        },
        {
          "type": "ITEM_DESTROYED",
          "timestamp": 1228760,
          "itemId": 3145
        },
        {
          "type": "ITEM_DESTROYED",
          "timestamp": 1228760,
          "itemId": 1058
        },
        {
          "type": "ITEM_PURCHASED",
          "timestamp": 1228760,
          "itemId": 4645
        },
        {
          "type": "ITEM_PURCHASED",
          "timestamp": 1236516,
          "itemId": 3113
        },
        {
          "type": "ITEM_PURCHASED",
          "timestamp": 1318477,
          "itemId": 1052
        },
        {
          "type": "ITEM_DESTROYED",
          "timestamp": 1427247,
          "itemId": 1052
        },
        {
          "type": "ITEM_PURCHASED",
          "timestamp": 1427247,
          "itemId": 3145
        },
        {
          "type": "ITEM_DESTROYED",
          "timestamp": 1553461,
          "itemId": 3145
        },
        {
          "type": "ITEM_DESTROYED",
          "timestamp": 1553461,
          "itemId": 3113
        },
        {
          "type": "ITEM_PURCHASED",
          "timestamp": 1553461,
          "itemId": 4646
        },
        {
          "type": "ITEM_PURCHASED",
          "timestamp": 1627362,
          "itemId": 1058
        },
        {
          "type": "ITEM_DESTROYED",
          "timestamp": 1844724,
          "itemId": 1058
        },
        {
          "type": "ITEM_PURCHASED",
          "timestamp": 1844724,
          "itemId": 3089
        },
        {
          "type": "ITEM_SOLD",
          "timestamp": 1947886,
          "itemId": 1056
        },
        {
          "type": "ITEM_PURCHASED",
          "timestamp": 1949089,
          "itemId": 4630
        },
        {
          "type": "ITEM_DESTROYED",
          "timestamp": 2179993,
          "itemId": 4630
        },
        {
          "type": "ITEM_PURCHASED",
          "timestamp": 2179993,
          "itemId": 3135
        },
        {
          "type": "ITEM_DESTROYED",
          "timestamp": 2182230,
          "itemId": 2139
        },
        {
          "type": "ITEM_PURCHASED",
          "timestamp": 2182230,
          "itemId": 2139
        },
        {
          "type": "ITEM_DESTROYED",
          "timestamp": 2237561,
          "itemId": 2139
        },
        {
          "type": "ITEM_PURCHASED",
          "timestamp": 2237561,
          "itemId": 2139
        }
      ],
      "final_items": [
        3135,
        6655,
        3020,
        4645,
        4646,
        3089,
        3340
      ]
    },
    {
      "participantId": 4,
      "championName": "MissFortune",
      "teamId": 100,
      "win": true,
      "lane": "BOTTOM",
      "gold_curve": [
        500,
        500,
        585,
        923,
        1294,
        1535,
        2255,
        2828,
        3032,
        3258,
        3862,
        3985,
        4447,
        5107,
        5311,
        5805,
        5927,
        6050,
        6475,
        7103,
        7269,
        7392,
        7792,
        8448,
        8595,
        8781,
        8903,
        9025,
        9456,
        9794,
        9958,
        10464,
        11585,
        12050,
        12736,
        12974,
        13416,
        13538,
        14543,
        15229
      ],
      "item_purchases": [
        {
          "type": "ITEM_PURCHASED",
          "timestamp": 9577,
          "itemId": 1083
        },
        {
          "type": "ITEM_PURCHASED",
          "timestamp": 419329,
          "itemId": 1037
        },
        {
          "type": "ITEM_PURCHASED",
          "timestamp": 420030,
          "itemId": 1036
        },
        {
          "type": "ITEM_PURCHASED",
          "timestamp": 420810,
          "itemId": 1036
        },
        {
          "type": "ITEM_PURCHASED",
          "timestamp": 422213,
          "itemId": 1018
        },
        {
          "type": "ITEM_DESTROYED",
          "timestamp": 483715,
          "itemId": 1036
        },
        {
          "type": "ITEM_DESTROYED",
          "timestamp": 483715,
          "itemId": 1036
        },
        {
          "type": "ITEM_PURCHASED",
          "timestamp": 483715,
          "itemId": 3133
        },
        {
          "type": "ITEM_DESTROYED",
          "timestamp": 628437,
          "itemId": 1037
        },
        {
          "type": "ITEM_DESTROYED",
          "timestamp": 628437,
          "itemId": 3133
        },
        {
          "type": "ITEM_DESTROYED",
          "timestamp": 628437,
          "itemId": 1018
        },
        {
          "type": "ITEM_PURCHASED",
          "timestamp": 628437,
          "itemId": 3508
        },
        {
          "type": "ITEM_PURCHASED",
          "timestamp": 630662,
          "itemId": 1036
        },
        {
          "type": "ITEM_PURCHASED",
          "timestamp": 835419,
          "itemId": 1037
        },
        {
          "type": "ITEM_DESTROYED",
          "timestamp": 836121,
          "itemId": 1036
        },
        {
          "type": "ITEM_PURCHASED",
          "timestamp": 836121,
          "itemId": 3134
        },
        {
          "type": "ITEM_PURCHASED",
          "timestamp": 914180,
          "itemId": 1018
        },
        {
          "type": "ITEM_DESTROYED",
          "timestamp": 1150156,
          "itemId": 1037
        },
        {
          "type": "ITEM_DESTROYED",
          "timestamp": 1150156,
          "itemId": 3134
        },
        {
          "type": "ITEM_DESTROYED",
          "timestamp": 1150156,
          "itemId": 1018
        },
        {
          "type": "ITEM_PURCHASED",
          "timestamp": 1150156,
          "itemId": 6676
        },
        {
          "type": "ITEM_PURCHASED",
          "timestamp": 1152795,
          "itemId": 1018
        },
        {
          "type": "ITEM_PURCHASED",
          "timestamp": 1222352,
          "itemId": 1036
        },
        {
          "type": "ITEM_PURCHASED",
          "timestamp": 1332801,
          "itemId": 1036
        },
        {
          "type": "ITEM_DESTROYED",
          "timestamp": 1423730,
          "itemId": 1036
        },
        {
          "type": "ITEM_DESTROYED",
          "timestamp": 1423730,
          "itemId": 1036
        },
        {
          "type": "ITEM_PURCHASED",
          "timestamp": 1423730,
          "itemId": 3035
        },
        {
          "type": "ITEM_PURCHASED",
          "timestamp": 1498434,
          "itemId": 1036
        },
        {
          "type": "ITEM_DESTROYED",
          "timestamp": 1779864,
          "itemId": 1036
        },
        {
          "type": "ITEM_DESTROYED",
          "timestamp": 1779864,
          "itemId": 3035
        },
        {
          "type": "ITEM_DESTROYED",
          "timestamp": 1779864,
          "itemId": 1018
        },
        {
          "type": "ITEM_PURCHASED",
          "timestamp": 1779864,
          "itemId": 3033
        },
        {
          "type": "ITEM_PURCHASED",
          "timestamp": 1917881,
          "itemId": 1038
        },
        {
          "type": "ITEM_PURCHASED",
          "timestamp": 1930564,
          "itemId": 1018
        },
        {
          "type": "ITEM_DESTROYED",
          "timestamp": 2158461,
          "itemId": 1038
        },
        {
          "type": "ITEM_DESTROYED",
          "timestamp": 2158461,
          "itemId": 1018
        },
        {
          "type": "ITEM_PURCHASED",
          "timestamp": 2158461,
          "itemId": 3031
        },
        {
          "type": "ITEM_PURCHASED",
          "timestamp": 2311158,
          "itemId": 6690
        }
      ],
      "final_items": [
        1083,
        3508,
        6676,
        3033,
        3031,
        6690,
        3340
      ]
    },
    {
      "participantId": 5,
      "championName": "Bard",
      "teamId": 100,
      "win": true,
      "lane": "UTILITY",
      "gold_curve": [
        500,
        500,
        572,
        758,
        953,
        1124,
        1794,
        1983,
        2285,
        2652,
        3950,
        4221,
        4874,
        5228,
        5486,
        5639,
        5976,
        6299,
        6456,
        6659,
        6981,
        7538,
        7741,
        7943,
        8254,
        8406,
        9649,
        9940,
        10350,
        10677,
        11202,
        11554,
        12166,
        12664,
        13248,
        13726,
        14316,
        14469,
        14928,
        15594
      ],
      "item_purchases": [
        {
          "type": "ITEM_PURCHASED",
          "timestamp": 9744,
          "itemId": 2003
        },
        {
          "type": "ITEM_PURCHASED",
          "timestamp": 9944,
          "itemId": 2003
        },
        {
          "type": "ITEM_PURCHASED",
          "timestamp": 396941,
          "itemId": 3009
        },
        {
          "type": "ITEM_PURCHASED",
          "timestamp": 402422,
          "itemId": 1028
        },
        {
          "type": "ITEM_PURCHASED",
          "timestamp": 404860,
          "itemId": 1029
        },
        {
          "type": "ITEM_DESTROYED",
          "timestamp": 408568,
          "itemId": 3340
        },
        {
          "type": "ITEM_PURCHASED",
          "timestamp": 408568,
          "itemId": 3364
        },
        {
          "type": "ITEM_PURCHASED",
          "timestamp": 409302,
          "itemId": 2055
        },
        {
          "type": "ITEM_DESTROYED",
          "timestamp": 453395,
          "itemId": 3865
        },
        {
          "type": "ITEM_DESTROYED",
          "timestamp": 481878,
          "itemId": 2055
        },
        {
          "type": "ITEM_DESTROYED",
          "timestamp": 545541,
          "itemId": 2003
        },
        {
          "type": "ITEM_DESTROYED",
          "timestamp": 568032,
          "itemId": 2003
        },
        {
          "type": "ITEM_DESTROYED",
          "timestamp": 654823,
          "itemId": 1029
        },
        {
          "type": "ITEM_PURCHASED",
          "timestamp": 654823,
          "itemId": 1031
        },
        {
          "type": "ITEM_PURCHASED",
          "timestamp": 655524,
          "itemId": 3066
        },
        {
          "type": "ITEM_PURCHASED",
          "timestamp": 656025,
          "itemId": 1028
        },
        {
          "type": "ITEM_DESTROYED",
          "timestamp": 790774,
          "itemId": 3866
        },
        {
          "type": "ITEM_DESTROYED",
          "timestamp": 793971,
          "itemId": 3867
        },
        {
          "type": "ITEM_DESTROYED",
          "timestamp": 812398,
          "itemId": 3066
        },
        {
          "type": "ITEM_DESTROYED",
          "timestamp": 812398,
          "itemId": 1028
        },
        {
          "type": "ITEM_DESTROYED",
          "timestamp": 812398,
          "itemId": 1031
        },
        {
          "type": "ITEM_PURCHASED",
          "timestamp": 812398,
          "itemId": 3742
        },
        {
          "type": "ITEM_PURCHASED",
          "timestamp": 814703,
          "itemId": 2508
        },
        {
          "type": "ITEM_PURCHASED",
          "timestamp": 1020894,
          "itemId": 1052
        },
        {
          "type": "ITEM_PURCHASED",
          "timestamp": 1021161,
          "itemId": 1028
        },
        {
          "type": "ITEM_DESTROYED",
          "timestamp": 1256825,
          "itemId": 1052
        },
        {
          "type": "ITEM_DESTROYED",
          "timestamp": 1256825,
          "itemId": 1028
        },
        {
          "type": "ITEM_PURCHASED",
          "timestamp": 1256825,
          "itemId": 3147
        },
        {
          "type": "ITEM_DESTROYED",
          "timestamp": 1261383,
          "itemId": 3147
        },
        {
          "type": "ITEM_DESTROYED",
          "timestamp": 1261383,
          "itemId": 2508
        },
        {
          "type": "ITEM_PURCHASED",
          "timestamp": 1261383,
          "itemId": 6653
        },
        {
          "type": "ITEM_PURCHASED",
          "timestamp": 1421024,
          "itemId": 1004
        },
        {
          "type": "ITEM_PURCHASED",
          "timestamp": 1421391,
          "itemId": 1052
        },
        {
          "type": "ITEM_PURCHASED",
          "timestamp": 1426444,
          "itemId": 1004
        },
        {
          "type": "ITEM_PURCHASED",
          "timestamp": 1426677,
          "itemId": 1052
        },
        {
          "type": "ITEM_DESTROYED",
          "timestamp": 1585174,
          "itemId": 1052
        },
        {
          "type": "ITEM_DESTROYED",
          "timestamp": 1585174,
          "itemId": 1004
        },
        {
          "type": "ITEM_PURCHASED",
          "timestamp": 1585174,
          "itemId": 2065
        },
        {
          "type": "ITEM_PURCHASED",
          "timestamp": 1880263,
          "itemId": 3916
        },
        {
          "type": "ITEM_DESTROYED",
          "timestamp": 1956521,
          "itemId": 3916
        },
        {
          "type": "ITEM_PURCHASED",
          "timestamp": 1956521,
          "itemId": 3165
        },
        {
          "type": "ITEM_DESTROYED",
          "timestamp": 2216552,
          "itemId": 2139
        },
        {
          "type": "ITEM_PURCHASED",
          "timestamp": 2216552,
          "itemId": 2139
        }
      ],
      "final_items": [
        3871,
        2065,
        6653,
        3742,
        3009,
        3165,
        3364
      ]
    },
    {
      "participantId": 6,
      "championName": "Malphite",
      "teamId": 200,
      "win": false,
      "lane": "TOP",
      "gold_curve": [
        500,
        500,
        618,
        944,
        1150,
        1441,
        1703,
        2000,
        2738,
        3212,
        3596,
        3873,
        4100,
        4592,
        4861,
        5215,
        5925,
        6217,
        6534,
        7261,
        7949,
        8092,
        8352,
        8475,
        8700,
        9080,
        9561,
        9747,
        10043,
        10597,
        10763,
        11066,
        11188,
        11316,
        11473,
        11630,
        12060,
        12182,
        12459,
        13717
      ],
      "item_purchases": [
        {
          "type": "ITEM_PURCHASED",
          "timestamp": 15427,
          "itemId": 1056
        },
        {
          "type": "ITEM_PURCHASED",
          "timestamp": 15427,
          "itemId": 2003
        },
        {
          "type": "ITEM_PURCHASED",
          "timestamp": 15427,
          "itemId": 2003
        },
        {
          "type": "ITEM_PURCHASED",
          "timestamp": 16195,
          "itemId": 3340
        },
        {
          "type": "ITEM_DESTROYED",
          "timestamp": 146511,
          "itemId": 2003
        },
        {
          "type": "ITEM_DESTROYED",
          "timestamp": 179097,
          "itemId": 2003
        },
        {
          "type": "ITEM_PURCHASED",
          "timestamp": 222050,
          "itemId": 1028
        },
        {
          "type": "ITEM_PURCHASED",
          "timestamp": 224522,
          "itemId": 2003
        },
        {
          "type": "ITEM_DESTROYED",
          "timestamp": 292370,
          "itemId": 2003
        },
        {
          "type": "ITEM_DESTROYED",
          "timestamp": 350622,
          "itemId": 1028
        },
        {
          "type": "ITEM_PURCHASED",
          "timestamp": 350622,
          "itemId": 6660
        },
        {
          "type": "ITEM_PURCHASED",
          "timestamp": 354423,
          "itemId": 2003
        },
        {
          "type": "ITEM_DESTROYED",
          "timestamp": 424885,
          "itemId": 2003
        },
        {
          "type": "ITEM_PURCHASED",
          "timestamp": 449420,
          "itemId": 1031
        },
        {
          "type": "ITEM_PURCHASED",
          "timestamp": 450322,
          "itemId": 1001
        },
        {
          "type": "ITEM_PURCHASED",
          "timestamp": 451425,
          "itemId": 2003
        },
        {
          "type": "ITEM_DESTROYED",
          "timestamp": 488906,
          "itemId": 2003
        },
        {
          "type": "ITEM_PURCHASED",
          "timestamp": 568066,
          "itemId": 1029
        },
        {
          "type": "ITEM_PURCHASED",
          "timestamp": 569636,
          "itemId": 2003
        },
        {
          "type": "ITEM_DESTROYED",
          "timestamp": 634169,
          "itemId": 2003
        },
        {
          "type": "ITEM_DESTROYED",
          "timestamp": 697169,
          "itemId": 6660
        },
        {
          "type": "ITEM_DESTROYED",
          "timestamp": 697169,
          "itemId": 1031
        },
        {
          "type": "ITEM_PURCHASED",
          "timestamp": 697169,
          "itemId": 3068
        },
        {
          "type": "ITEM_PURCHASED",
          "timestamp": 698505,
          "itemId": 2003
        },
        {
          "type": "ITEM_DESTROYED",
          "timestamp": 749222,
          "itemId": 2003
        },
        {
          "type": "ITEM_DESTROYED",
          "timestamp": 786866,
          "itemId": 1029
        },
        {
          "type": "ITEM_PURCHASED",
          "timestamp": 786866,
          "itemId": 3076
        },
        {
          "type": "ITEM_PURCHASED",
          "timestamp": 788303,
          "itemId": 2003
        },
        {
          "type": "ITEM_DESTROYED",
          "timestamp": 930213,
          "itemId": 2003
        },
        {
          "type": "ITEM_DESTROYED",
          "timestamp": 975481,
          "itemId": 1001
        },
        {
          "type": "ITEM_PURCHASED",
          "timestamp": 975481,
          "itemId": 3047
        },
        {
          "type": "ITEM_PURCHASED",
          "timestamp": 978844,
          "itemId": 1029
        },
        {
          "type": "ITEM_PURCHASED",
          "timestamp": 980213,
          "itemId": 2003
        },
        {
          "type": "ITEM_DESTROYED",
          "timestamp": 1006304,
          "itemId": 2003
        },
        {
          "type": "ITEM_DESTROYED",
          "timestamp": 1129954,
          "itemId": 3076
        },
        {
          "type": "ITEM_DESTROYED",
          "timestamp": 1129954,
          "itemId": 1029
        },
        {
          "type": "ITEM_PURCHASED",
          "timestamp": 1129954,
          "itemId": 3075
        },
        {
          "type": "ITEM_PURCHASED",
          "timestamp": 1227562,
          "itemId": 1029
        },
        {
          "type": "ITEM_PURCHASED",
          "timestamp": 1227896,
          "itemId": 1029
        },
        {
          "type": "ITEM_DESTROYED",
          "timestamp": 1296699,
          "itemId": 1029
        },
        {
          "type": "ITEM_DESTROYED",
          "timestamp": 1296699,
          "itemId": 1029
        },
        {
          "type": "ITEM_PURCHASED",
          "timestamp": 1296699,
          "itemId": 3082
        },
        {
          "type": "ITEM_PURCHASED",
          "timestamp": 1409602,
          "itemId": 1029
        },
        {
          "type": "ITEM_DESTROYED",
          "timestamp": 1614689,
          "itemId": 3082
        },
        {
          "type": "ITEM_DESTROYED",
          "timestamp": 1614689,
          "itemId": 1029
        },
        {
          "type": "ITEM_PURCHASED",
          "timestamp": 1614689,
          "itemId": 3110
        },
        {
          "type": "ITEM_PURCHASED",
          "timestamp": 1859937,
          "itemId": 1011
        },
        {
          "type": "ITEM_SOLD",
          "timestamp": 1861549,
          "itemId": 1056
        },
        {
          "type": "ITEM_PURCHASED",
          "timestamp": 1863856,
          "itemId": 1033
        },
        {
          "type": "ITEM_DESTROYED",
          "timestamp": 1972159,
          "itemId": 1033
        },
        {
          "type": "ITEM_PURCHASED",
          "timestamp": 1972159,
          "itemId": 1057
        }
      ],
      "final_items": [
        1057,
        3068,
        3075,
        3047,
        3110,
        1011,
        3340
      ]
    },
    {
      "participantId": 7,
      "championName": "Jax",
      "teamId": 200,
      "win": false,
      "lane": "JUNGLE",
      "gold_curve": [
        500,
        820,
        861,
        1164,
        1476,
        2160,
        2467,
        2794,
        3027,
        3677,
        4306,
        4711,
        5114,
        5676,
        5998,
        6658,
        7345,
        7518,
        7750,
        8328,
        8745,
        9173,
        10795,
        10918,
        11555,
        11957,
        12248,
        12410,
        12981,
        13139,
        13261,
        13498,
        13791,
        14018,
        14396,
        14519,
        14856,
        15117,
        15515,
        15883
      ],
      "item_purchases": [
        {
          "type": "ITEM_PURCHASED",
          "timestamp": 5902,
          "itemId": 1101
        },
        {
          "type": "ITEM_PURCHASED",
          "timestamp": 98857,
          "itemId": 1036
        },
        {
          "type": "ITEM_PURCHASED",
          "timestamp": 347816,
          "itemId": 3057
        },
        {
          "type": "ITEM_PURCHASED",
          "timestamp": 347883,
          "itemId": 1028
        },
        {
          "type": "ITEM_PURCHASED",
          "timestamp": 347950,
          "itemId": 1042
        },
        {
          "type": "ITEM_DESTROYED",
          "timestamp": 554461,
          "itemId": 3057
        },
        {
          "type": "ITEM_DESTROYED",
          "timestamp": 554461,
          "itemId": 1028
        },
        {
          "type": "ITEM_DESTROYED",
          "timestamp": 554461,
          "itemId": 1036
        },
        {
          "type": "ITEM_DESTROYED",
          "timestamp": 554461,
          "itemId": 1042
        },
        {
          "type": "ITEM_PURCHASED",
          "timestamp": 554461,
          "itemId": 3078
        },
        {
          "type": "ITEM_PURCHASED",
          "timestamp": 556031,
          "itemId": 1029
        },
        {
          "type": "ITEM_DESTROYED",
          "timestamp": 679357,
          "itemId": 2422
        },
        {
          "type": "ITEM_DESTROYED",
          "timestamp": 679357,
          "itemId": 1029
        },
        {
          "type": "ITEM_PURCHASED",
          "timestamp": 679357,
          "itemId": 3047
        },
        {
          "type": "ITEM_PURCHASED",
          "timestamp": 1008110,
          "itemId": 2021
        },
        {
          "type": "ITEM_PURCHASED",
          "timestamp": 1008177,
          "itemId": 3133
        },
        {
          "type": "ITEM_PURCHASED",
          "timestamp": 1008244,
          "itemId": 1028
        },
        {
          "type": "ITEM_DESTROYED",
          "timestamp": 1066651,
          "itemId": 1101
        },
        {
          "type": "ITEM_DESTROYED",
          "timestamp": 1224857,
          "itemId": 2021
        },
        {
          "type": "ITEM_DESTROYED",
          "timestamp": 1224857,
          "itemId": 3133
        },
        {
          "type": "ITEM_DESTROYED",
          "timestamp": 1224857,
          "itemId": 1028
        },
        {
          "type": "ITEM_PURCHASED",
          "timestamp": 1224857,
          "itemId": 6610
        },
        {
          "type": "ITEM_PURCHASED",
          "timestamp": 1226494,
          "itemId": 1058
        },
        {
          "type": "ITEM_DESTROYED",
          "timestamp": 1535373,
          "itemId": 1058
        },
        {
          "type": "ITEM_PURCHASED",
          "timestamp": 1535373,
          "itemId": 3157
        },
        {
          "type": "ITEM_DESTROYED",
          "timestamp": 1536447,
          "itemId": 3047
        },
        {
          "type": "ITEM_PURCHASED",
          "timestamp": 1536447,
          "itemId": 3174
        },
        {
          "type": "ITEM_PURCHASED",
          "timestamp": 1538384,
          "itemId": 1028
        },
        {
          "type": "ITEM_DESTROYED",
          "timestamp": 1551992,
          "itemId": 3340
        },
        {
          "type": "ITEM_PURCHASED",
          "timestamp": 1551992,
          "itemId": 3364
        },
        {
          "type": "ITEM_PURCHASED",
          "timestamp": 1787312,
          "itemId": 1037
        },
        {
          "type": "ITEM_DESTROYED",
          "timestamp": 1903505,
          "itemId": 1028
        },
        {
          "type": "ITEM_PURCHASED",
          "timestamp": 1903505,
          "itemId": 2021
        },
        {
          "type": "ITEM_DESTROYED",
          "timestamp": 2204595,
          "itemId": 1037
        },
        {
          "type": "ITEM_DESTROYED",
          "timestamp": 2204595,
          "itemId": 2021
        },
        {
          "type": "ITEM_PURCHASED",
          "timestamp": 2204595,
          "itemId": 3053
        },
        {
          "type": "ITEM_PURCHASED",
          "timestamp": 2261771,
          "itemId": 1043
        }
      ],
      "final_items": [
        3078,
        6610,
        3157,
        3174,
        3053,
        1043,
        3364
      ]
    },
    {
      "participantId": 8,
      "championName": "Ahri",
      "teamId": 200,
      "win": false,
      "lane": "MIDDLE",
      "gold_curve": [
        500,
        500,
        632,
        874,
        1066,
        1215,
        1428,
        1703,
        1903,
        2178,
        2364,
        2542,
        3382,
        3760,
        3883,
        4047,
        4470,
        4856,
        4999,
        5397,
        5570,
        6773,
        6900,
        7077,
        7493,
        7615,
        8235,
        8358,
        8480,
        8665,
        8793,
        8915,
        9037,
        9160,
        9643,
        10239,
        10452,
        10574,
        10927,
        11254
      ],
      "item_purchases": [
        {
          "type": "ITEM_PURCHASED",
          "timestamp": 4061,
          "itemId": 1056
        },
        {
          "type": "ITEM_PURCHASED",
          "timestamp": 4061,
          "itemId": 2003
        },
        {
          "type": "ITEM_PURCHASED",
          "timestamp": 4061,
          "itemId": 2003
        },
        {
          "type": "ITEM_PURCHASED",
          "timestamp": 4766,
          "itemId": 3364
        },
        {
          "type": "ITEM_DESTROYED",
          "timestamp": 5167,
          "itemId": 3364
        },
        {
          "type": "ITEM_PURCHASED",
          "timestamp": 5167,
          "itemId": 3340
        },
        {
          "type": "ITEM_DESTROYED",
          "timestamp": 125903,
          "itemId": 2003
        },
        {
          "type": "ITEM_DESTROYED",
          "timestamp": 141149,
          "itemId": 2003
        },
        {
          "type": "ITEM_PURCHASED",
          "timestamp": 150119,
          "itemId": 2022
        },
        {
          "type": "ITEM_PURCHASED",
          "timestamp": 256656,
          "itemId": 1001
        },
        {
          "type": "ITEM_DESTROYED",
          "timestamp": 391723,
          "itemId": 1001
        },
        {
          "type": "ITEM_DESTROYED",
          "timestamp": 391723,
          "itemId": 2022
        },
        {
          "type": "ITEM_PURCHASED",
          "timestamp": 391723,
          "itemId": 3158
        },
        {
          "type": "ITEM_PURCHASED",
          "timestamp": 459108,
          "itemId": 1027
        },
        {
          "type": "ITEM_PURCHASED",
          "timestamp": 594196,
          "itemId": 1052
        },
        {
          "type": "ITEM_PURCHASED",
          "timestamp": 595465,
          "itemId": 2022
        },
        {
          "type": "ITEM_PURCHASED",
          "timestamp": 695499,
          "itemId": 1026
        },
        {
          "type": "ITEM_DESTROYED",
          "timestamp": 837023,
          "itemId": 1052
        },
        {
          "type": "ITEM_DESTROYED",
          "timestamp": 837023,
          "itemId": 1027
        },
        {
          "type": "ITEM_DESTROYED",
          "timestamp": 837023,
          "itemId": 2022
        },
        {
          "type": "ITEM_PURCHASED",
          "timestamp": 837023,
          "itemId": 3802
        },
        {
          "type": "ITEM_DESTROYED",
          "timestamp": 944842,
          "itemId": 3802
        },
        {
          "type": "ITEM_DESTROYED",
          "timestamp": 944842,
          "itemId": 1026
        },
        {
          "type": "ITEM_PURCHASED",
          "timestamp": 944842,
          "itemId": 3118
        },
        {
          "type": "ITEM_PURCHASED",
          "timestamp": 948950,
          "itemId": 1027
        },
        {
          "type": "ITEM_PURCHASED",
          "timestamp": 1038761,
          "itemId": 1052
        },
        {
          "type": "ITEM_DESTROYED",
          "timestamp": 1136167,
          "itemId": 1052
        },
        {
          "type": "ITEM_DESTROYED",
          "timestamp": 1136167,
          "itemId": 1027
        },
        {
          "type": "ITEM_PURCHASED",
          "timestamp": 1136167,
          "itemId": 3802
        },
        {
          "type": "ITEM_DESTROYED",
          "timestamp": 1138741,
          "itemId": 1052
        },
        {
          "type": "ITEM_PURCHASED",
          "timestamp": 1138741,
          "itemId": 2508
        },
        {
          "type": "ITEM_DESTROYED",
          "timestamp": 1261116,
          "itemId": 1027
        },
        {
          "type": "ITEM_PURCHASED",
          "timestamp": 1261116,
          "itemId": 3802
        },
        {
          "type": "ITEM_DESTROYED",
          "timestamp": 1424197,
          "itemId": 3802
        },
        {
          "type": "ITEM_DESTROYED",
          "timestamp": 1424197,
          "itemId": 2508
        },
        {
          "type": "ITEM_PURCHASED",
          "timestamp": 1424197,
          "itemId": 2503
        },
        {
          "type": "ITEM_PURCHASED",
          "timestamp": 1426878,
          "itemId": 1052
        },
        {
          "type": "ITEM_DESTROYED",
          "timestamp": 1553734,
          "itemId": 1052
        },
        {
          "type": "ITEM_PURCHASED",
          "timestamp": 1553734,
          "itemId": 3108
        },
        {
          "type": "ITEM_PURCHASED",
          "timestamp": 1554577,
          "itemId": 1052
        },
        {
          "type": "ITEM_SOLD",
          "timestamp": 1640354,
          "itemId": 1056
        },
        {
          "type": "ITEM_PURCHASED",
          "timestamp": 1641523,
          "itemId": 2022
        },
        {
          "type": "ITEM_DESTROYED",
          "timestamp": 1663163,
          "itemId": 1052
        },
        {
          "type": "ITEM_DESTROYED",
          "timestamp": 1663163,
          "itemId": 2022
        },
        {
          "type": "ITEM_PURCHASED",
          "timestamp": 1663163,
          "itemId": 3108
        },
        {
          "type": "ITEM_DESTROYED",
          "timestamp": 2073858,
          "itemId": 3108
        },
        {
          "type": "ITEM_DESTROYED",
          "timestamp": 2073858,
          "itemId": 3108
        },
        {
          "type": "ITEM_PURCHASED",
          "timestamp": 2073858,
          "itemId": 4628
        },
        {
          "type": "ITEM_DESTROYED",
          "timestamp": 2075762,
          "itemId": 3158
        },
        {
          "type": "ITEM_PURCHASED",
          "timestamp": 2075762,
          "itemId": 3171
        },
        {
          "type": "ITEM_PURCHASED",
          "timestamp": 2160532,
          "itemId": 1052
        },
        {
          "type": "ITEM_DESTROYED",
          "timestamp": 2287131,
          "itemId": 1052
        },
        {
          "type": "ITEM_PURCHASED",
          "timestamp": 2287131,
          "itemId": 3113
        }
      ],
      "final_items": [
        4628,
        3171,
        3118,
        2503,
        3113,
        0,
        3340
      ]
    },
    {
      "participantId": 9,
      "championName": "Ashe",
      "teamId": 200,
      "win": false,
      "lane": "BOTTOM",
      "gold_curve": [
        500,
        537,
        656,
        946,
        1349,
        1691,
        1855,
        2034,
        2810,
        3057,
        3430,
        3708,
        4032,
        4260,
        5159,
        5531,
        5765,
        6696,
        7401,
        7755,
        8088,
        9026,
        9673,
        9964,
        10424,
        11164,
        11985,
        12121,
        12396,
        12519,
        12816,
        13666,
        13788,
        14126,
        14249,
        15570,
        16091,
        16214,
        18036,
        18153
      ],
      "item_purchases": [
        {
          "type": "ITEM_PURCHASED",
          "timestamp": 9744,
          "itemId": 1055
        },
        {
          "type": "ITEM_PURCHASED",
          "timestamp": 9744,
          "itemId": 2003
        },
        {
          "type": "ITEM_DESTROYED",
          "timestamp": 171677,
          "itemId": 2010
        },
        {
          "type": "ITEM_DESTROYED",
          "timestamp": 238773,
          "itemId": 2003
        },
        {
          "type": "ITEM_DESTROYED",
          "timestamp": 245259,
          "itemId": 2010
        },
        {
          "type": "ITEM_PURCHASED",
          "timestamp": 336731,
          "itemId": 1001
        },
        {
          "type": "ITEM_PURCHASED",
          "timestamp": 337199,
          "itemId": 6690
        },
        {
          "type": "ITEM_PURCHASED",
          "timestamp": 339503,
          "itemId": 2055
        },
        {
          "type": "ITEM_DESTROYED",
          "timestamp": 362674,
          "itemId": 2055
        },
        {
          "type": "ITEM_DESTROYED",
          "timestamp": 387782,
          "itemId": 2010
        },
        {
          "type": "ITEM_PURCHASED",
          "timestamp": 410310,
          "itemId": 1036
        },
        {
          "type": "ITEM_DESTROYED",
          "timestamp": 511019,
          "itemId": 1036
        },
        {
          "type": "ITEM_PURCHASED",
          "timestamp": 511019,
          "itemId": 3051
        },
        {
          "type": "ITEM_PURCHASED",
          "timestamp": 608874,
          "itemId": 1042
        },
        {
          "type": "ITEM_DESTROYED",
          "timestamp": 735123,
          "itemId": 6690
        },
        {
          "type": "ITEM_DESTROYED",
          "timestamp": 735123,
          "itemId": 3051
        },
        {
          "type": "ITEM_DESTROYED",
          "timestamp": 735123,
          "itemId": 1042
        },
        {
          "type": "ITEM_PURCHASED",
          "timestamp": 735123,
          "itemId": 6672
        },
        {
          "type": "ITEM_DESTROYED",
          "timestamp": 883923,
          "itemId": 1001
        },
        {
          "type": "ITEM_PURCHASED",
          "timestamp": 883923,
          "itemId": 3006
        },
        {
          "type": "ITEM_PURCHASED",
          "timestamp": 885226,
          "itemId": 1018
        },
        {
          "type": "ITEM_DESTROYED",
          "timestamp": 889325,
          "itemId": 3340
        },
        {
          "type": "ITEM_PURCHASED",
          "timestamp": 889325,
          "itemId": 3363
        },
        {
          "type": "ITEM_DESTROYED",
          "timestamp": 1002911,
          "itemId": 1018
        },
        {
          "type": "ITEM_PURCHASED",
          "timestamp": 1002911,
          "itemId": 3086
        },
        {
          "type": "ITEM_PURCHASED",
          "timestamp": 1002978,
          "itemId": 1042
        },
        {
          "type": "ITEM_PURCHASED",
          "timestamp": 1003045,
          "itemId": 1042
        },
        {
          "type": "ITEM_DESTROYED",
          "timestamp": 1129084,
          "itemId": 1042
        },
        {
          "type": "ITEM_DESTROYED",
          "timestamp": 1129084,
          "itemId": 3086
        },
        {
          "type": "ITEM_DESTROYED",
          "timestamp": 1129084,
          "itemId": 1042
        },
        {
          "type": "ITEM_PURCHASED",
          "timestamp": 1129084,
          "itemId": 3046
        },
        {
          "type": "ITEM_PURCHASED",
          "timestamp": 1228460,
          "itemId": 1038
        },
        {
          "type": "ITEM_PURCHASED",
          "timestamp": 1410838,
          "itemId": 1037
        },
        {
          "type": "ITEM_DESTROYED",
          "timestamp": 1462355,
          "itemId": 1038
        },
        {
          "type": "ITEM_DESTROYED",
          "timestamp": 1462355,
          "itemId": 1037
        },
        {
          "type": "ITEM_PURCHASED",
          "timestamp": 1462355,
          "itemId": 3031
        },
        {
          "type": "ITEM_PURCHASED",
          "timestamp": 1571832,
          "itemId": 1036
        },
        {
          "type": "ITEM_SOLD",
          "timestamp": 1575439,
          "itemId": 1055
        },
        {
          "type": "ITEM_PURCHASED",
          "timestamp": 1577582,
          "itemId": 1036
        },
        {
          "type": "ITEM_DESTROYED",
          "timestamp": 1583270,
          "itemId": 1036
        },
        {
          "type": "ITEM_DESTROYED",
          "timestamp": 1583270,
          "itemId": 1036
        },
        {
          "type": "ITEM_PURCHASED",
          "timestamp": 1583270,
          "itemId": 3035
        },
        {
          "type": "ITEM_PURCHASED",
          "timestamp": 1775529,
          "itemId": 1018
        },
        {
          "type": "ITEM_DESTROYED",
          "timestamp": 1884909,
          "itemId": 3035
        },
        {
          "type": "ITEM_DESTROYED",
          "timestamp": 1884909,
          "itemId": 1018
        },
        {
          "type": "ITEM_PURCHASED",
          "timestamp": 1884909,
          "itemId": 3036
        },
        {
          "type": "ITEM_DESTROYED",
          "timestamp": 1921142,
          "itemId": 3035
        },
        {
          "type": "ITEM_DESTROYED",
          "timestamp": 1921142,
          "itemId": 1018
        },
        {
          "type": "ITEM_PURCHASED",
          "timestamp": 1921142,
          "itemId": 3036
        },
        {
          "type": "ITEM_PURCHASED",
          "timestamp": 2101680,
          "itemId": 1038
        },
        {
          "type": "ITEM_DESTROYED",
          "timestamp": 2243473,
          "itemId": 1038
        },
        {
          "type": "ITEM_PURCHASED",
          "timestamp": 2243473,
          "itemId": 3026
        },
        {
          "type": "ITEM_DESTROYED",
          "timestamp": 2244508,
          "itemId": 2140
        },
        {
          "type": "ITEM_PURCHASED",
          "timestamp": 2244508,
          "itemId": 2140
        },
        {
          "type": "ITEM_SOLD",
          "timestamp": 2291723,
          "itemId": 3026
        }
      ],
      "final_items": [
        3036,
        6672,
        3006,
        3046,
        3031,
        3026,
        3363
      ]
    },
    {
      "participantId": 10,
      "championName": "Thresh",
      "teamId": 200,
      "win": false,
      "lane": "UTILITY",
      "gold_curve": [
        500,
        537,
        605,
        760,
        946,
        1131,
        1292,
        1446,
        1791,
        1957,
        2153,
        3126,
        3470,
        3828,
        4255,
        4830,
        4982,
        5437,
        5769,
        6113,
        6316,
        6468,
        6713,
        6867,
        7173,
        7515,
        7768,
        7921,
        8088,
        8355,
        8695,
        9335,
        9808,
        9960,
        10113,
        10453,
        10615,
        10768,
        11060,
        11626
      ],
      "item_purchases": [
        {
          "type": "ITEM_PURCHASED",
          "timestamp": 6403,
          "itemId": 3340
        },
        {
          "type": "ITEM_PURCHASED",
          "timestamp": 6737,
          "itemId": 2003
        },
        {
          "type": "ITEM_PURCHASED",
          "timestamp": 6904,
          "itemId": 2003
        },
        {
          "type": "ITEM_DESTROYED",
          "timestamp": 226927,
          "itemId": 2003
        },
        {
          "type": "ITEM_PURCHASED",
          "timestamp": 365046,
          "itemId": 3067
        },
        {
          "type": "ITEM_DESTROYED",
          "timestamp": 425052,
          "itemId": 2010
        },
        {
          "type": "ITEM_DESTROYED",
          "timestamp": 425386,
          "itemId": 2003
        },
        {
          "type": "ITEM_PURCHASED",
          "timestamp": 441218,
          "itemId": 2055
        },
        {
          "type": "ITEM_DESTROYED",
          "timestamp": 441619,
          "itemId": 3340
        },
        {
          "type": "ITEM_PURCHASED",
          "timestamp": 441619,
          "itemId": 3364
        },
        {
          "type": "ITEM_PURCHASED",
          "timestamp": 517776,
          "itemId": 1001
        },
        {
          "type": "ITEM_DESTROYED",
          "timestamp": 584705,
          "itemId": 2010
        },
        {
          "type": "ITEM_DESTROYED",
          "timestamp": 597469,
          "itemId": 3865
        },
        {
          "type": "ITEM_PURCHASED",
          "timestamp": 610812,
          "itemId": 1029
        },
        {
          "type": "ITEM_DESTROYED",
          "timestamp": 659432,
          "itemId": 2055
        },
        {
          "type": "ITEM_DESTROYED",
          "timestamp": 718856,
          "itemId": 3067
        },
        {
          "type": "ITEM_DESTROYED",
          "timestamp": 718856,
          "itemId": 1029
        },
        {
          "type": "ITEM_PURCHASED",
          "timestamp": 718856,
          "itemId": 3190
        },
        {
          "type": "ITEM_PURCHASED",
          "timestamp": 725433,
          "itemId": 2055
        },
        {
          "type": "ITEM_DESTROYED",
          "timestamp": 762332,
          "itemId": 2055
        },
        {
          "type": "ITEM_DESTROYED",
          "timestamp": 828771,
          "itemId": 2010
        },
        {
          "type": "ITEM_DESTROYED",
          "timestamp": 905302,
          "itemId": 1001
        },
        {
          "type": "ITEM_PURCHASED",
          "timestamp": 905302,
          "itemId": 3009
        },
        {
          "type": "ITEM_PURCHASED",
          "timestamp": 916752,
          "itemId": 3067
        },
        {
          "type": "ITEM_PURCHASED",
          "timestamp": 918756,
          "itemId": 1004
        },
        {
          "type": "ITEM_DESTROYED",
          "timestamp": 976752,
          "itemId": 3866
        },
        {
          "type": "ITEM_DESTROYED",
          "timestamp": 1008010,
          "itemId": 1004
        },
        {
          "type": "ITEM_PURCHASED",
          "timestamp": 1008010,
          "itemId": 3114
        },
        {
          "type": "ITEM_PURCHASED",
          "timestamp": 1011120,
          "itemId": 2055
        },
        {
          "type": "ITEM_DESTROYED",
          "timestamp": 1041935,
          "itemId": 3867
        },
        {
          "type": "ITEM_DESTROYED",
          "timestamp": 1319913,
          "itemId": 3067
        },
        {
          "type": "ITEM_DESTROYED",
          "timestamp": 1319913,
          "itemId": 3114
        },
        {
          "type": "ITEM_PURCHASED",
          "timestamp": 1319913,
          "itemId": 3107
        },
        {
          "type": "ITEM_PURCHASED",
          "timestamp": 1343622,
          "itemId": 1028
        },
        {
          "type": "ITEM_DESTROYED",
          "timestamp": 1449764,
          "itemId": 1028
        },
        {
          "type": "ITEM_PURCHASED",
          "timestamp": 1449764,
          "itemId": 3067
        },
        {
          "type": "ITEM_SOLD",
          "timestamp": 1452804,
          "itemId": 2055
        },
        {
          "type": "ITEM_PURCHASED",
          "timestamp": 1454741,
          "itemId": 1029
        },
        {
          "type": "ITEM_DESTROYED",
          "timestamp": 1579586,
          "itemId": 1029
        },
        {
          "type": "ITEM_PURCHASED",
          "timestamp": 1579586,
          "itemId": 1031
        },
        {
          "type": "ITEM_DESTROYED",
          "timestamp": 1910261,
          "itemId": 3067
        },
        {
          "type": "ITEM_DESTROYED",
          "timestamp": 1910261,
          "itemId": 1031
        },
        {
          "type": "ITEM_PURCHASED",
          "timestamp": 1910261,
          "itemId": 3109
        },
        {
          "type": "ITEM_PURCHASED",
          "timestamp": 1932831,
          "itemId": 3067
        },
        {
          "type": "ITEM_DESTROYED",
          "timestamp": 1934159,
          "itemId": 3009
        },
        {
          "type": "ITEM_PURCHASED",
          "timestamp": 1934159,
          "itemId": 3170
        },
        {
          "type": "ITEM_DESTROYED",
          "timestamp": 2304712,
          "itemId": 3067
        },
        {
          "type": "ITEM_PURCHASED",
          "timestamp": 2304712,
          "itemId": 3050
        }
      ],
      "final_items": [
        3107,
        3876,
        3170,
        3190,
        3109,
        3050,
        3364
      ]
    }
  ]
}